Workbook

Sheet README
A1: FP&A Budget vs Actual and Rolling Forecast – Finance Analytics Portfolio Project
A2: BZME Insights | Sector: Finance / FP&A | Tool: Excel (formula-driven)
A4: BUSINESS PROBLEM
A5: A distributor's sales are on budget, but profit is falling behind. Finance managers need to see where the gap comes from and how the full year will end up.
A7: BUSINESS QUESTIONS
A8: 1. How do revenue, margin, costs and profit compare with budget, month by month and year to date?
A9: 2. Which lines explain the profit gap, and which variances matter most?
A10: 3. How will the full year finish if the current run-rate continues?
A11: 4. How does the outlook change under Upside and Downside scenarios?
A12: 5. What should management do next?
A14: HOW THE WORKBOOK IS BUILT
A15: Budget: monthly P&L for Jan-Dec 2026 (revenue by segment, COGS, operating costs, depreciation, finance costs, tax).
... A40: Re-forecast monthly and track actuals against the Upside/Downside range.

Sheet Dashboard
B1: Budget vs Actual & Rolling Forecast Dashboard
B2: Fictional Kenyan FMCG distributor (Savanna Fresh Foods Ltd) | Synthetic data | YTD to 30 Sep 2026, KES '000 | Prepared by BZME Insights
B3: Forecast scenario: | C3: =Assumptions!B18 -> Base
B5: YTD Performance (Jan-Sep 2026)
B6: KPI | C6: Actual | D6: Budget | E6: Variance | F6: Var % | G6: Status
B7: Revenue | C7: =Actuals!K7 -> 976785 | D7: =Budget!O7 -> 968480 | E7: =Variance!E8 -> 8305 | F7: =Variance!F8 -> 0.0085752932 | G7: =Variance!G8 -> On budget
B8: Gross Profit | C8: =Actuals!K12 -> 276809 | D8: =Budget!O12 -> 284858.8 | E8: =Variance!E10 -> -8049.8 | F8: =Variance!F10 -> -0.028258913 | G8: =Variance!G10 -> Adverse
B9: Gross Margin % | C9: =Actuals!K13 -> 0.28338785 | D9: =Budget!O13 -> 0.29412977 | E9: =C9-D9 -> -0.010741921 | F9: pp | G9: =IF(ABS(E9)<=0.001,"On budget",IF(E9>0,"Favourable","Adverse")) -> Adverse
B10: Operating Expenses | C10: =Actuals!K19 -> 203774 | D10: =Budget!O19 -> 198490 | E10: =Variance!E16 -> -5284 | F10: =Variance!F16 -> -0.026620988 | G10: =Variance!G16 -> Adverse
B11: EBITDA | C11: =Actuals!K20 -> 73035 | D11: =Budget!O20 -> 86368.8 | E11: =Variance!E17 -> -13333.8 | F11: =Variance!F17 -> -0.15438214 | G11: =Variance!G17 -> Adverse
B12: EBITDA Margin % | C12: =Actuals!K21 -> 0.074770804 | D12: =Budget!O21 -> 0.089179746 | E12: =C12-D12 -> -0.014408941 | F12: pp | G12: =IF(ABS(E12)<=0.001,"On budget",IF(E12>0,"Favourable","Adverse")) -> Adverse
B13: Net Profit | C13: =Actuals!K27 -> 31830.4 | D13: =Budget!O27 -> 41432.16 | E13: =Variance!E23 -> -9601.76 | F13: =Variance!F23 -> -0.23174655 | G13: =Variance!G23 -> Adverse
B15: FY2026 Outlook (Actual Jan-Sep + Forecast Oct-Dec)
B16: KPI | C16: Outlook | D16: Budget | E16: Variance | F16: Var %
B17: Gross Profit | C17: =Forecast!N12 -> 381859.36 | D17: =Forecast!O12 -> 393047.2 | E17: =C17-D17 -> -11187.841 | F17: =IF(D17=0,0,E17/ABS(D17)) -> -0.028464371
B18: EBITDA | C18: =Forecast!N20 -> 103794.62 | D18: =Forecast!O20 -> 122117.2 | E18: =C18-D18 -> -18322.583 | F18: =IF(D18=0,0,E18/ABS(D18)) -> -0.15004097
B19: Net Profit | C19: =Forecast!N27 -> 47272.132 | D19: =Forecast!O27 -> 60366.04 | E19: =C19-D19 -> -13093.908 | F19: =IF(D19=0,0,E19/ABS(D19)) -> -0.21690851
B20: Revenue | C20: =Forecast!N7 -> 1346892 | D20: =Forecast!O7 -> 1335790 | E20: =C20-D20 -> 11102.018 | F20: =IF(D20=0,0,E20/ABS(D20)) -> 0.0083112002
B21: Margin variances in percentage points. Variance column: positive = favourable.
B40: Key findings
B41: ="1. Revenue is "&TEXT(ABS(Variance!F8),"0.0%")&IF(Variance!E8>=0," above"," below")&" budget YTD (KES "&TEXT(ABS(Variance!E8),"#,##0")&"k). Wholesale ("&TEXT(Variance!F6,"+0.0%;-0.0%")&") is the growth driver; E-commerce ("&TEXT(Variance!F7,"+0.0%;-0.0%")&") and Retail ("&TEXT(Variance!F5,"+0.0%;-0.0%")&") are behind." -> 1. Revenue is 0.9% above budget YTD (KES 8,305k). Wholesale (+5.2%) is the growth driver; E-commerce (-7.5%) and Retail (-2.4%) are behind.
B42: ="2. Gross margin is "&TEXT(Actuals!K13,"0.0%")&" versus a budget of "&TEXT(Budget!O13,"0.0%")&": input cost inflation and lower-margin wholesale volume changed margin by "&TEXT((Actuals!K13-Budget!O13)*100,"+0.0;-0.0")&" percentage points." -> 2. Gross margin is 28.3% versus a budget of 29.4%: input cost inflation and lower-margin wholesale volume changed margin by -1.1 percentage points.
B43: ="3. Operating expenses are "&TEXT(ABS(Variance!F16),"0.0%")&IF(Variance!E16>=0," under"," over")&" budget. Logistics is "&TEXT(ABS(Variance!F13),"0.0%")&IF(Variance!E13>=0," under"," over")&" budget (fuel and routing); salaries are "&TEXT(ABS(Variance!F11),"0.0%")&IF(Variance!E11>=0," under"," over")&" budget (early hires)." -> 3. Operating expenses are 2.7% over budget. Logistics is 8.0% over budget (fuel and routing); salaries are 3.1% over budget (early hires).
B44: ="4. EBITDA is KES "&TEXT(Actuals!K20,"#,##0")&"k YTD ("&TEXT(Actuals!K21,"0.0%")&" margin) versus a budget of KES "&TEXT(Budget!O20,"#,##0")&"k ("&TEXT(Budget!O21,"0.0%")&")." -> 4. EBITDA is KES 73,035k YTD (7.5% margin) versus a budget of KES 86,369k (8.9%).
B45: ="5. Under the "&Assumptions!B18&" scenario, FY2026 net profit is forecast at KES "&TEXT(Forecast!N27,"#,##0")&"k, "&TEXT(ABS(Forecast!Q27),"0.0%")&IF(Forecast!P27>=0," above"," below")&" the budget of KES "&TEXT(Forecast!O27,"#,##0")&"k." -> 5. Under the Base scenario, FY2026 net profit is forecast at KES 47,272k, 21.7% below the budget of KES 60,366k.
B47: Recommended actions
B48: 1. Renegotiate fuel and route contracts and consolidate deliveries to bring logistics back toward budget.
B49: 2. Review wholesale contract pricing to protect margin on the new hotel-chain volume.
B50: 3. Accelerate the e-commerce recovery with targeted Q4 promotions inside the marketing budget.
B51: 4. Phase marketing spend evenly across months to avoid catch-up overspend.
B52: 5. Re-forecast monthly and track actuals against the Upside/Downside range on the Assumptions sheet.
B54: Sheets: Assumptions (inputs & method) | Budget | Actuals | Variance | Forecast. All figures synthetic. Change the scenario on Assumptions!B18.

Sheet Assumptions
A1: Assumptions & Methodology
A2: Blue = hardcoded input | Yellow = cell to change | Black = formula
A3: General
A4: Company (fictional) | B4: Savanna Fresh Foods Ltd
A5: Reporting currency / units | B5: KES '000
A6: Financial year | B6: FY2026 (Jan-Dec)
A7: Actuals through | B7: September 2026
A9: Budget COGS as % of revenue
A10: Retail Distribution | B10: 0.64 | C10: Synthetic assumption set at budget stage
A11: Wholesale | B11: 0.76
A12: E-commerce | B12: 0.68
A14: Tax
A15: Corporate income tax rate | B15: 0.3 | C15: Assumed 30% (simplified; applied monthly to positive profit before tax)
A17: Forecast scenario
A18: Selected scenario | B18: Base
A19: Revenue multiplier applied to Q4 run-rate | B19: =INDEX(B22:B24,MATCH(B18,A22:A24,0)) -> 1
A21: Scenario | B21: Multiplier | C21: Description
A22: Base | B22: 1 | C22: Q4 revenue follows each segment's YTD run-rate versus budget
A23: Upside | B23: 1.05 | C23: Festive demand and faster e-commerce recovery beat the run-rate
A24: Downside | B24: 0.92 | C24: Weaker consumer spending and supply disruption
A26: Methodology notes
A27: 1. All figures are SYNTHETIC, created for portfolio purposes. No real company data is used.
A28: 2. Variance convention: positive = favourable to profit, negative = adverse (income lines: Actual - Budget; cost lines: Budget - Actual).
A29: 3. Status 'On budget' means variance within +/-1% of budget.
A30: 4. Forecast Oct-Dec revenue = budget month x segment YTD actual/budget ratio x scenario multiplier.
A31: 5. Forecast COGS % = segment YTD actual COGS % of revenue.
A32: 6. Forecast opex lines = budget month x line's YTD actual/budget ratio (run-rate assumption). Depreciation = budget. Finance costs = budget.
A33: 7. Margin variances on the Dashboard are shown in percentage points (actual % minus budget %).

Sheet Budget
A1: FY2026 Budget - Monthly P&L
A2: Synthetic data. Blue = hardcoded budget inputs; black = formulas.
A3: KES '000 | B3: Jan | C3: Feb | D3: Mar | E3: Apr | F3: May | G3: Jun | H3: Jul | I3: Aug | J3: Sep | K3: Oct | L3: Nov | M3: Dec | N3: FY2026 | O3: YTD Sep
A4: Retail Distribution revenue | B4: 37600 | C4: 36950 | D4: 39110 | E4: 39670 | F4: 40640 | G4: 40390 | H4: 41370 | I4: 41940 | J4: 42520 | K4: 43100 | L4: 44510 | M4: 48020 | N4: =SUM(B4:M4) -> 495820 | O4: =SUM(B4:J4) -> 360190
A5: Wholesale revenue | B5: 51700 | C5: 50750 | D5: 53670 | E5: 54390 | F5: 55660 | G5: 55270 | H5: 56550 | I5: 57280 | J5: 58010 | K5: 58740 | L5: 60620 | M5: 65340 | N5: =SUM(B5:M5) -> 677980 | O5: =SUM(B5:J5) -> 493280
A6: E-commerce revenue | B6: 11280 | C6: 11260 | D6: 12110 | E6: 12470 | F6: 12960 | G6: 13070 | H6: 13570 | I6: 13950 | J6: 14340 | K6: 14730 | L6: 15410 | M6: 16840 | N6: =SUM(B6:M6) -> 161990 | O6: =SUM(B6:J6) -> 115010
A7: Total Revenue | B7: =SUM(B4:B6) -> 100580 | C7: =SUM(C4:C6) -> 98960 | D7: =SUM(D4:D6) -> 104890 | E7: =SUM(E4:E6) -> 106530 | F7: =SUM(F4:F6) -> 109260 | G7: =SUM(G4:G6) -> 108730 | H7: =SUM(H4:H6) -> 111490 | I7: =SUM(I4:I6) -> 113170 | ... M7: =SUM(M4:M6) -> 130200 | N7: =SUM(B7:M7) -> 1335790 | O7: =SUM(B7:J7) -> 968480
A8: COGS - Retail Distribution | B8: =B4*Assumptions!$B$10 -> 24064 | C8: =C4*Assumptions!$B$10 -> 23648 | D8: =D4*Assumptions!$B$10 -> 25030.4 | E8: =E4*Assumptions!$B$10 -> 25388.8 | F8: =F4*Assumptions!$B$10 -> 26009.6 | G8: =G4*Assumptions!$B$10 -> 25849.6 | H8: =H4*Assumptions!$B$10 -> 26476.8 | I8: =I4*Assumptions!$B$10 -> 26841.6 | ... M8: =M4*Assumptions!$B$10 -> 30732.8 | N8: =SUM(B8:M8) -> 317324.8 | O8: =SUM(B8:J8) -> 230521.6
A9: COGS - Wholesale | B9: =B5*Assumptions!$B$11 -> 39292 | C9: =C5*Assumptions!$B$11 -> 38570 | D9: =D5*Assumptions!$B$11 -> 40789.2 | E9: =E5*Assumptions!$B$11 -> 41336.4 | F9: =F5*Assumptions!$B$11 -> 42301.6 | G9: =G5*Assumptions!$B$11 -> 42005.2 | H9: =H5*Assumptions!$B$11 -> 42978 | I9: =I5*Assumptions!$B$11 -> 43532.8 | ... M9: =M5*Assumptions!$B$11 -> 49658.4 | N9: =SUM(B9:M9) -> 515264.8 | O9: =SUM(B9:J9) -> 374892.8
A10: COGS - E-commerce | B10: =B6*Assumptions!$B$12 -> 7670.4 | C10: =C6*Assumptions!$B$12 -> 7656.8 | D10: =D6*Assumptions!$B$12 -> 8234.8 | E10: =E6*Assumptions!$B$12 -> 8479.6 | F10: =F6*Assumptions!$B$12 -> 8812.8 | G10: =G6*Assumptions!$B$12 -> 8887.6 | H10: =H6*Assumptions!$B$12 -> 9227.6 | I10: =I6*Assumptions!$B$12 -> 9486 | ... M10: =M6*Assumptions!$B$12 -> 11451.2 | N10: =SUM(B10:M10) -> 110153.2 | O10: =SUM(B10:J10) -> 78206.8
A11: Total COGS | B11: =SUM(B8:B10) -> 71026.4 | C11: =SUM(C8:C10) -> 69874.8 | D11: =SUM(D8:D10) -> 74054.4 | E11: =SUM(E8:E10) -> 75204.8 | F11: =SUM(F8:F10) -> 77124 | G11: =SUM(G8:G10) -> 76742.4 | H11: =SUM(H8:H10) -> 78682.4 | I11: =SUM(I8:I10) -> 79860.4 | ... M11: =SUM(M8:M10) -> 91842.4 | N11: =SUM(B11:M11) -> 942742.8 | O11: =SUM(B11:J11) -> 683621.2
A12: Gross Profit | B12: =B7-B11 -> 29553.6 | C12: =C7-C11 -> 29085.2 | D12: =D7-D11 -> 30835.6 | E12: =E7-E11 -> 31325.2 | F12: =F7-F11 -> 32136 | G12: =G7-G11 -> 31987.6 | H12: =H7-H11 -> 32807.6 | I12: =I7-I11 -> 33309.6 | ... M12: =M7-M11 -> 38357.6 | N12: =SUM(B12:M12) -> 393047.2 | O12: =SUM(B12:J12) -> 284858.8
A13: Gross Margin % | B13: =IF(B7=0,0,B12/B7) -> 0.29383178 | C13: =IF(C7=0,0,C12/C7) -> 0.29390865 | D13: =IF(D7=0,0,D12/D7) -> 0.29398036 | E13: =IF(E7=0,0,E12/E7) -> 0.2940505 | F13: =IF(F7=0,0,F12/F7) -> 0.29412411 | G13: =IF(G7=0,0,G12/G7) -> 0.29419296 | H13: =IF(H7=0,0,H12/H7) -> 0.29426496 | I13: =IF(I7=0,0,I12/I7) -> 0.29433242 | ... O13: =IF(O7=0,0,O12/O7) -> 0.29412977
A14: Salaries & Benefits | B14: 9200 | C14: 9200 | D14: 9200 | E14: 9200 | F14: 9200 | G14: 9200 | H14: 9480 | I14: 9480 | J14: 9480 | K14: 9480 | L14: 9480 | M14: 9480 | N14: =SUM(B14:M14) -> 112080 | O14: =SUM(B14:J14) -> 83640
A15: Marketing & Promotions | B15: 2800 | C15: 2800 | D15: 3000 | E15: 3000 | F15: 3000 | G15: 3000 | H15: 3200 | I15: 3400 | J15: 3400 | K15: 3600 | L15: 4200 | M15: 4800 | N15: =SUM(B15:M15) -> 40200 | O15: =SUM(B15:J15) -> 27600
A16: Logistics & Distribution | B16: 5230 | C16: 5150 | D16: 5450 | E16: 5540 | F16: 5680 | G16: 5650 | H16: 5800 | I16: 5880 | J16: 5970 | K16: 6060 | L16: 6270 | M16: 6770 | N16: =SUM(B16:M16) -> 69450 | O16: =SUM(B16:J16) -> 50350
A17: Rent & Utilities | B17: 2300 | C17: 2300 | D17: 2300 | E17: 2300 | F17: 2300 | G17: 2300 | H17: 2300 | I17: 2300 | J17: 2300 | K17: 2300 | L17: 2300 | M17: 2300 | N17: =SUM(B17:M17) -> 27600 | O17: =SUM(B17:J17) -> 20700
A18: Admin & IT | B18: 1800 | C18: 1800 | D18: 1800 | E18: 1800 | F18: 1800 | G18: 1800 | H18: 1800 | I18: 1800 | J18: 1800 | K18: 1800 | L18: 1800 | M18: 1800 | N18: =SUM(B18:M18) -> 21600 | O18: =SUM(B18:J18) -> 16200
A19: Total Operating Expenses | B19: =SUM(B14:B18) -> 21330 | C19: =SUM(C14:C18) -> 21250 | D19: =SUM(D14:D18) -> 21750 | E19: =SUM(E14:E18) -> 21840 | F19: =SUM(F14:F18) -> 21980 | G19: =SUM(G14:G18) -> 21950 | H19: =SUM(H14:H18) -> 22580 | I19: =SUM(I14:I18) -> 22860 | ... M19: =SUM(M14:M18) -> 25150 | N19: =SUM(B19:M19) -> 270930 | O19: =SUM(B19:J19) -> 198490
A20: EBITDA | B20: =B12-B19 -> 8223.6 | C20: =C12-C19 -> 7835.2 | D20: =D12-D19 -> 9085.6 | E20: =E12-E19 -> 9485.2 | F20: =F12-F19 -> 10156 | G20: =G12-G19 -> 10037.6 | H20: =H12-H19 -> 10227.6 | I20: =I12-I19 -> 10449.6 | ... M20: =M12-M19 -> 13207.6 | N20: =SUM(B20:M20) -> 122117.2 | O20: =SUM(B20:J20) -> 86368.8
A21: EBITDA Margin % | B21: =IF(B7=0,0,B20/B7) -> 0.081761782 | C21: =IF(C7=0,0,C20/C7) -> 0.079175424 | D21: =IF(D7=0,0,D20/D7) -> 0.086620269 | E21: =IF(E7=0,0,E20/E7) -> 0.08903783 | F21: =IF(F7=0,0,F20/F7) -> 0.09295259 | G21: =IF(G7=0,0,G20/G7) -> 0.092316748 | H21: =IF(H7=0,0,H20/H7) -> 0.091735582 | I21: =IF(I7=0,0,I20/I7) -> 0.092335425 | ... O21: =IF(O7=0,0,O20/O7) -> 0.089179746
A22: Depreciation | B22: 1600 | C22: 1600 | D22: 1600 | E22: 1600 | F22: 1600 | G22: 1600 | H22: 1600 | I22: 1600 | J22: 1600 | K22: 1600 | L22: 1600 | M22: 1600 | N22: =SUM(B22:M22) -> 19200 | O22: =SUM(B22:J22) -> 14400
A23: Operating Profit (EBIT) | B23: =B20-B22 -> 6623.6 | C23: =C20-C22 -> 6235.2 | D23: =D20-D22 -> 7485.6 | E23: =E20-E22 -> 7885.2 | F23: =F20-F22 -> 8556 | G23: =G20-G22 -> 8437.6 | H23: =H20-H22 -> 8627.6 | I23: =I20-I22 -> 8849.6 | ... M23: =M20-M22 -> 11607.6 | N23: =SUM(B23:M23) -> 102917.2 | O23: =SUM(B23:J23) -> 71968.8
A24: Finance Costs | B24: 1500 | C24: 1480 | D24: 1460 | E24: 1440 | F24: 1420 | G24: 1400 | H24: 1380 | I24: 1360 | J24: 1340 | K24: 1320 | L24: 1300 | M24: 1280 | N24: =SUM(B24:M24) -> 16680 | O24: =SUM(B24:J24) -> 12780
A25: Profit Before Tax | B25: =B23-B24 -> 5123.6 | C25: =C23-C24 -> 4755.2 | D25: =D23-D24 -> 6025.6 | E25: =E23-E24 -> 6445.2 | F25: =F23-F24 -> 7136 | G25: =G23-G24 -> 7037.6 | H25: =H23-H24 -> 7247.6 | I25: =I23-I24 -> 7489.6 | ... M25: =M23-M24 -> 10327.6 | N25: =SUM(B25:M25) -> 86237.2 | O25: =SUM(B25:J25) -> 59188.8
A26: Income Tax | B26: =MAX(0,B25)*Assumptions!$B$15 -> 1537.08 | C26: =MAX(0,C25)*Assumptions!$B$15 -> 1426.56 | D26: =MAX(0,D25)*Assumptions!$B$15 -> 1807.68 | E26: =MAX(0,E25)*Assumptions!$B$15 -> 1933.56 | F26: =MAX(0,F25)*Assumptions!$B$15 -> 2140.8 | G26: =MAX(0,G25)*Assumptions!$B$15 -> 2111.28 | H26: =MAX(0,H25)*Assumptions!$B$15 -> 2174.28 | I26: =MAX(0,I25)*Assumptions!$B$15 -> 2246.88 | ... M26: =MAX(0,M25)*Assumptions!$B$15 -> 3098.28 | N26: =SUM(B26:M26) -> 25871.16 | O26: =SUM(B26:J26) -> 17756.64
A27: Net Profit | B27: =B25-B26 -> 3586.52 | C27: =C25-C26 -> 3328.64 | D27: =D25-D26 -> 4217.92 | E27: =E25-E26 -> 4511.64 | F27: =F25-F26 -> 4995.2 | G27: =G25-G26 -> 4926.32 | H27: =H25-H26 -> 5073.32 | I27: =I25-I26 -> 5242.72 | ... M27: =M25-M26 -> 7229.32 | N27: =SUM(B27:M27) -> 60366.04 | O27: =SUM(B27:J27) -> 41432.16
A29: Budget lines 8-10 (COGS) = segment revenue x COGS % on Assumptions. Revenue, opex, depreciation and finance costs are synthetic inputs.

Sheet Actuals
A1: FY2026 Actuals - Jan to Sep
A2: Synthetic data. Blue = hardcoded actuals; black = formulas.
A3: KES '000 | B3: Jan | C3: Feb | D3: Mar | E3: Apr | F3: May | G3: Jun | H3: Jul | I3: Aug | J3: Sep | K3: YTD Sep
A4: Retail Distribution revenue | B4: 36325 | C4: 36226 | D4: 38302 | E4: 38530 | F4: 39550 | G4: 39152 | H4: 40710 | I4: 41313 | J4: 41390 | K4: =SUM(B4:J4) -> 351498
A5: Wholesale revenue | B5: 51703 | C5: 51077 | D5: 57405 | E5: 58005 | F5: 59134 | G5: 58749 | H5: 59651 | I5: 61717 | J5: 61476 | K5: =SUM(B5:J5) -> 518917
A6: E-commerce revenue | B6: 9929 | C6: 9968 | D6: 10583 | E6: 10919 | F6: 11428 | G6: 12544 | H6: 13338 | I6: 13686 | J6: 13975 | K6: =SUM(B6:J6) -> 106370
A7: Total Revenue | B7: =SUM(B4:B6) -> 97957 | C7: =SUM(C4:C6) -> 97271 | D7: =SUM(D4:D6) -> 106290 | E7: =SUM(E4:E6) -> 107454 | F7: =SUM(F4:F6) -> 110112 | G7: =SUM(G4:G6) -> 110445 | H7: =SUM(H4:H6) -> 113699 | I7: =SUM(I4:I6) -> 116716 | J7: =SUM(J4:J6) -> 116841 | K7: =SUM(B7:J7) -> 976785
A8: COGS - Retail Distribution | B8: 23591 | C8: 23487 | D8: 24782 | E8: 24961 | F8: 25628 | G8: 25367 | H8: 26375 | I8: 26781 | J8: 26743 | K8: =SUM(B8:J8) -> 227715
A9: COGS - Wholesale | B9: 39212 | C9: 38765 | D9: 44427 | E9: 44867 | F9: 45561 | G9: 45358 | H9: 46046 | I9: 47687 | J9: 47498 | K9: =SUM(B9:J9) -> 399421
A10: COGS - E-commerce | B10: 6790 | C10: 6833 | D10: 7268 | E10: 7488 | F10: 7828 | G10: 8569 | H10: 9122 | I10: 9364 | J10: 9578 | K10: =SUM(B10:J10) -> 72840
A11: Total COGS | B11: =SUM(B8:B10) -> 69593 | C11: =SUM(C8:C10) -> 69085 | D11: =SUM(D8:D10) -> 76477 | E11: =SUM(E8:E10) -> 77316 | F11: =SUM(F8:F10) -> 79017 | G11: =SUM(G8:G10) -> 79294 | H11: =SUM(H8:H10) -> 81543 | I11: =SUM(I8:I10) -> 83832 | J11: =SUM(J8:J10) -> 83819 | K11: =SUM(B11:J11) -> 699976
A12: Gross Profit | B12: =B7-B11 -> 28364 | C12: =C7-C11 -> 28186 | D12: =D7-D11 -> 29813 | E12: =E7-E11 -> 30138 | F12: =F7-F11 -> 31095 | G12: =G7-G11 -> 31151 | H12: =H7-H11 -> 32156 | I12: =I7-I11 -> 32884 | J12: =J7-J11 -> 33022 | K12: =SUM(B12:J12) -> 276809
A13: Gross Margin % | B13: =IF(B7=0,0,B12/B7) -> 0.28955562 | C13: =IF(C7=0,0,C12/C7) -> 0.28976776 | D13: =IF(D7=0,0,D12/D7) -> 0.28048735 | E13: =IF(E7=0,0,E12/E7) -> 0.2804735 | F13: =IF(F7=0,0,F12/F7) -> 0.28239429 | G13: =IF(G7=0,0,G12/G7) -> 0.28204989 | H13: =IF(H7=0,0,H12/H7) -> 0.28281691 | I13: =IF(I7=0,0,I12/I7) -> 0.28174372 | ... K13: =IF(K7=0,0,K12/K7) -> 0.28338785
A14: Salaries & Benefits | B14: 9484 | C14: 9446 | D14: 9499 | E14: 9482 | F14: 9495 | G14: 9455 | H14: 9795 | I14: 9788 | J14: 9761 | K14: =SUM(B14:J14) -> 86205
A15: Marketing & Promotions | B15: 2383 | C15: 2395 | D15: 2575 | E15: 2526 | F15: 3006 | G15: 2978 | H15: 3208 | I15: 3808 | J15: 3810 | K15: =SUM(B15:J15) -> 26689
A16: Logistics & Distribution | B16: 5696 | C16: 5554 | D16: 5888 | E16: 6021 | F16: 6133 | G16: 6019 | H16: 6256 | I16: 6346 | J16: 6446 | K16: =SUM(B16:J16) -> 54359
A17: Rent & Utilities | B17: 2300 | C17: 2300 | D17: 2300 | E17: 2392 | F17: 2392 | G17: 2392 | H17: 2392 | I17: 2392 | J17: 2392 | K17: =SUM(B17:J17) -> 21252
A18: Admin & IT | B18: 1694 | C18: 1703 | D18: 1678 | E18: 1687 | F18: 1706 | G18: 1699 | H18: 1691 | I18: 1705 | J18: 1706 | K18: =SUM(B18:J18) -> 15269
A19: Total Operating Expenses | B19: =SUM(B14:B18) -> 21557 | C19: =SUM(C14:C18) -> 21398 | D19: =SUM(D14:D18) -> 21940 | E19: =SUM(E14:E18) -> 22108 | F19: =SUM(F14:F18) -> 22732 | G19: =SUM(G14:G18) -> 22543 | H19: =SUM(H14:H18) -> 23342 | I19: =SUM(I14:I18) -> 24039 | J19: =SUM(J14:J18) -> 24115 | K19: =SUM(B19:J19) -> 203774
A20: EBITDA | B20: =B12-B19 -> 6807 | C20: =C12-C19 -> 6788 | D20: =D12-D19 -> 7873 | E20: =E12-E19 -> 8030 | F20: =F12-F19 -> 8363 | G20: =G12-G19 -> 8608 | H20: =H12-H19 -> 8814 | I20: =I12-I19 -> 8845 | J20: =J12-J19 -> 8907 | K20: =SUM(B20:J20) -> 73035
A21: EBITDA Margin % | B21: =IF(B7=0,0,B20/B7) -> 0.069489674 | C21: =IF(C7=0,0,C20/C7) -> 0.069784417 | D21: =IF(D7=0,0,D20/D7) -> 0.074070938 | E21: =IF(E7=0,0,E20/E7) -> 0.074729652 | F21: =IF(F7=0,0,F20/F7) -> 0.075949942 | G21: =IF(G7=0,0,G20/G7) -> 0.077939246 | H21: =IF(H7=0,0,H20/H7) -> 0.077520471 | I21: =IF(I7=0,0,I20/I7) -> 0.075782241 | ... K21: =IF(K7=0,0,K20/K7) -> 0.074770804
A22: Depreciation | B22: 1600 | C22: 1600 | D22: 1600 | E22: 1600 | F22: 1600 | G22: 1600 | H22: 1600 | I22: 1600 | J22: 1600 | K22: =SUM(B22:J22) -> 14400
A23: Operating Profit (EBIT) | B23: =B20-B22 -> 5207 | C23: =C20-C22 -> 5188 | D23: =D20-D22 -> 6273 | E23: =E20-E22 -> 6430 | F23: =F20-F22 -> 6763 | G23: =G20-G22 -> 7008 | H23: =H20-H22 -> 7214 | I23: =I20-I22 -> 7245 | J23: =J20-J22 -> 7307 | K23: =SUM(B23:J23) -> 58635
A24: Finance Costs | B24: 1545 | C24: 1524 | D24: 1504 | E24: 1483 | F24: 1463 | G24: 1442 | H24: 1421 | I24: 1401 | J24: 1380 | K24: =SUM(B24:J24) -> 13163
A25: Profit Before Tax | B25: =B23-B24 -> 3662 | C25: =C23-C24 -> 3664 | D25: =D23-D24 -> 4769 | E25: =E23-E24 -> 4947 | F25: =F23-F24 -> 5300 | G25: =G23-G24 -> 5566 | H25: =H23-H24 -> 5793 | I25: =I23-I24 -> 5844 | J25: =J23-J24 -> 5927 | K25: =SUM(B25:J25) -> 45472
A26: Income Tax | B26: =MAX(0,B25)*Assumptions!$B$15 -> 1098.6 | C26: =MAX(0,C25)*Assumptions!$B$15 -> 1099.2 | D26: =MAX(0,D25)*Assumptions!$B$15 -> 1430.7 | E26: =MAX(0,E25)*Assumptions!$B$15 -> 1484.1 | F26: =MAX(0,F25)*Assumptions!$B$15 -> 1590 | G26: =MAX(0,G25)*Assumptions!$B$15 -> 1669.8 | H26: =MAX(0,H25)*Assumptions!$B$15 -> 1737.9 | I26: =MAX(0,I25)*Assumptions!$B$15 -> 1753.2 | J26: =MAX(0,J25)*Assumptions!$B$15 -> 1778.1 | K26: =SUM(B26:J26) -> 13641.6
A27: Net Profit | B27: =B25-B26 -> 2563.4 | C27: =C25-C26 -> 2564.8 | D27: =D25-D26 -> 3338.3 | E27: =E25-E26 -> 3462.9 | F27: =F25-F26 -> 3710 | G27: =G25-G26 -> 3896.2 | H27: =H25-H26 -> 4055.1 | I27: =I25-I26 -> 4090.8 | J27: =J25-J26 -> 4148.9 | K27: =SUM(B27:J27) -> 31830.4

Sheet Variance
A1: YTD Variance Analysis - Actual vs Budget (Jan-Sep 2026)
A2: Variance: positive = favourable to profit, negative = adverse. On budget = within +/-1%.
A4: Line (KES '000) | B4: Type | C4: Actual YTD | D4: Budget YTD | E4: Variance | F4: Variance % | G4: Status | H4: Driver / commentary
A5: Retail Distribution revenue | B5: Income | C5: =Actuals!K4 -> 351498 | D5: =Budget!O4 -> 360190 | E5: =IF(B5="Income",C5-D5,D5-C5) -> -8692 | F5: =IF(D5=0,0,E5/ABS(D5)) -> -0.024131708 | G5: =IF(ABS(F5)<=0.01,"On budget",IF(E5>0,"Favourable","Adverse")) -> Adverse | H5: Retail weaker footfall in Q2; promotions limited
A6: Wholesale revenue | B6: Income | C6: =Actuals!K5 -> 518917 | D6: =Budget!O5 -> 493280 | E6: =IF(B6="Income",C6-D6,D6-C6) -> 25637 | F6: =IF(D6=0,0,E6/ABS(D6)) -> 0.051972511 | G6: =IF(ABS(F6)<=0.01,"On budget",IF(E6>0,"Favourable","Adverse")) -> Favourable | H6: New hotel-chain contract from March, lifting volume
A7: E-commerce revenue | B7: Income | C7: =Actuals!K6 -> 106370 | D7: =Budget!O6 -> 115010 | E7: =IF(B7="Income",C7-D7,D7-C7) -> -8640 | F7: =IF(D7=0,0,E7/ABS(D7)) -> -0.075123902 | G7: =IF(ABS(F7)<=0.01,"On budget",IF(E7>0,"Favourable","Adverse")) -> Adverse | H7: App relaunch delayed to June; recovering through Q3
A8: Total Revenue | B8: Income | C8: =Actuals!K7 -> 976785 | D8: =Budget!O7 -> 968480 | E8: =IF(B8="Income",C8-D8,D8-C8) -> 8305 | F8: =IF(D8=0,0,E8/ABS(D8)) -> 0.0085752932 | G8: =IF(ABS(F8)<=0.01,"On budget",IF(E8>0,"Favourable","Adverse")) -> On budget | H8: Wholesale growth outweighs e-commerce and retail shortfalls
A9: Total COGS | B9: Cost | C9: =Actuals!K11 -> 699976 | D9: =Budget!O11 -> 683621.2 | E9: =IF(B9="Income",C9-D9,D9-C9) -> -16354.8 | F9: =IF(D9=0,0,E9/ABS(D9)) -> -0.023923775 | G9: =IF(ABS(F9)<=0.01,"On budget",IF(E9>0,"Favourable","Adverse")) -> Adverse | H9: Input cost inflation plus lower-margin wholesale mix
A10: Gross Profit | B10: Income | C10: =Actuals!K12 -> 276809 | D10: =Budget!O12 -> 284858.8 | E10: =IF(B10="Income",C10-D10,D10-C10) -> -8049.8 | F10: =IF(D10=0,0,E10/ABS(D10)) -> -0.028258913 | G10: =IF(ABS(F10)<=0.01,"On budget",IF(E10>0,"Favourable","Adverse")) -> Adverse | H10: Volume gains offset by margin pressure
A11: Salaries & Benefits | B11: Cost | C11: =Actuals!K14 -> 86205 | D11: =Budget!O14 -> 83640 | E11: =IF(B11="Income",C11-D11,D11-C11) -> -2565 | F11: =IF(D11=0,0,E11/ABS(D11)) -> -0.030667145 | G11: =IF(ABS(F11)<=0.01,"On budget",IF(E11>0,"Favourable","Adverse")) -> Adverse | H11: Two sales hires brought forward
A12: Marketing & Promotions | B12: Cost | C12: =Actuals!K15 -> 26689 | D12: =Budget!O15 -> 27600 | E12: =IF(B12="Income",C12-D12,D12-C12) -> 911 | F12: =IF(D12=0,0,E12/ABS(D12)) -> 0.033007246 | G12: =IF(ABS(F12)<=0.01,"On budget",IF(E12>0,"Favourable","Adverse")) -> Favourable | H12: Underspent Jan-Apr, catch-up in Aug-Sep
A13: Logistics & Distribution | B13: Cost | C13: =Actuals!K16 -> 54359 | D13: =Budget!O16 -> 50350 | E13: =IF(B13="Income",C13-D13,D13-C13) -> -4009 | F13: =IF(D13=0,0,E13/ABS(D13)) -> -0.079622642 | G13: =IF(ABS(F13)<=0.01,"On budget",IF(E13>0,"Favourable","Adverse")) -> Adverse | H13: Higher fuel prices and longer delivery routes
A14: Rent & Utilities | B14: Cost | C14: =Actuals!K17 -> 21252 | D14: =Budget!O17 -> 20700 | E14: =IF(B14="Income",C14-D14,D14-C14) -> -552 | F14: =IF(D14=0,0,E14/ABS(D14)) -> -0.026666667 | G14: =IF(ABS(F14)<=0.01,"On budget",IF(E14>0,"Favourable","Adverse")) -> Adverse | H14: Utility tariff increase from April
A15: Admin & IT | B15: Cost | C15: =Actuals!K18 -> 15269 | D15: =Budget!O18 -> 16200 | E15: =IF(B15="Income",C15-D15,D15-C15) -> 931 | F15: =IF(D15=0,0,E15/ABS(D15)) -> 0.057469136 | G15: =IF(ABS(F15)<=0.01,"On budget",IF(E15>0,"Favourable","Adverse")) -> Favourable | H15: Software renewals delayed
A16: Total Operating Expenses | B16: Cost | C16: =Actuals!K19 -> 203774 | D16: =Budget!O19 -> 198490 | E16: =IF(B16="Income",C16-D16,D16-C16) -> -5284 | F16: =IF(D16=0,0,E16/ABS(D16)) -> -0.026620988 | G16: =IF(ABS(F16)<=0.01,"On budget",IF(E16>0,"Favourable","Adverse")) -> Adverse | H16: Logistics overspend partly offset by savings
A17: EBITDA | B17: Income | C17: =Actuals!K20 -> 73035 | D17: =Budget!O20 -> 86368.8 | E17: =IF(B17="Income",C17-D17,D17-C17) -> -13333.8 | F17: =IF(D17=0,0,E17/ABS(D17)) -> -0.15438214 | G17: =IF(ABS(F17)<=0.01,"On budget",IF(E17>0,"Favourable","Adverse")) -> Adverse
A18: Depreciation | B18: Cost | C18: =Actuals!K22 -> 14400 | D18: =Budget!O22 -> 14400 | E18: =IF(B18="Income",C18-D18,D18-C18) -> 0 | F18: =IF(D18=0,0,E18/ABS(D18)) -> 0 | G18: =IF(ABS(F18)<=0.01,"On budget",IF(E18>0,"Favourable","Adverse")) -> On budget
A19: Operating Profit (EBIT) | B19: Income | C19: =Actuals!K23 -> 58635 | D19: =Budget!O23 -> 71968.8 | E19: =IF(B19="Income",C19-D19,D19-C19) -> -13333.8 | F19: =IF(D19=0,0,E19/ABS(D19)) -> -0.18527195 | G19: =IF(ABS(F19)<=0.01,"On budget",IF(E19>0,"Favourable","Adverse")) -> Adverse
A20: Finance Costs | B20: Cost | C20: =Actuals!K24 -> 13163 | D20: =Budget!O24 -> 12780 | E20: =IF(B20="Income",C20-D20,D20-C20) -> -383 | F20: =IF(D20=0,0,E20/ABS(D20)) -> -0.029968701 | G20: =IF(ABS(F20)<=0.01,"On budget",IF(E20>0,"Favourable","Adverse")) -> Adverse | H20: Slightly higher borrowing cost
A21: Profit Before Tax | B21: Income | C21: =Actuals!K25 -> 45472 | D21: =Budget!O25 -> 59188.8 | E21: =IF(B21="Income",C21-D21,D21-C21) -> -13716.8 | F21: =IF(D21=0,0,E21/ABS(D21)) -> -0.23174655 | G21: =IF(ABS(F21)<=0.01,"On budget",IF(E21>0,"Favourable","Adverse")) -> Adverse
A22: Income Tax | B22: Cost | C22: =Actuals!K26 -> 13641.6 | D22: =Budget!O26 -> 17756.64 | E22: =IF(B22="Income",C22-D22,D22-C22) -> 4115.04 | F22: =IF(D22=0,0,E22/ABS(D22)) -> 0.23174655 | G22: =IF(ABS(F22)<=0.01,"On budget",IF(E22>0,"Favourable","Adverse")) -> Favourable
A23: Net Profit | B23: Income | C23: =Actuals!K27 -> 31830.4 | D23: =Budget!O27 -> 41432.16 | E23: =IF(B23="Income",C23-D23,D23-C23) -> -9601.76 | F23: =IF(D23=0,0,E23/ABS(D23)) -> -0.23174655 | G23: =IF(ABS(F23)<=0.01,"On budget",IF(E23>0,"Favourable","Adverse")) -> Adverse

Sheet Forecast
A1: FY2026 Rolling Forecast - Actuals (Jan-Sep) + Forecast (Oct-Dec)
A2: Scenario is selected on the Assumptions sheet (cell B18). Green = linked from Actuals/Budget.
A3: KES '000 | B3: Jan | C3: Feb | D3: Mar | E3: Apr | F3: May | G3: Jun | H3: Jul | I3: Aug | J3: Sep | K3: Oct | L3: Nov | M3: Dec | N3: FY Outlook | O3: FY Budget | P3: Var (Out-Bud) | Q3: Var %
A4: Retail Distribution revenue | B4: =Actuals!B4 -> 36325 | C4: =Actuals!C4 -> 36226 | D4: =Actuals!D4 -> 38302 | E4: =Actuals!E4 -> 38530 | F4: =Actuals!F4 -> 39550 | G4: =Actuals!G4 -> 39152 | H4: =Actuals!H4 -> 40710 | I4: =Actuals!I4 -> 41313 | J4: =Actuals!J4 -> 41390 | K4: =Budget!K4*(Actuals!$K4/Budget!$O4)*Assumptions!$B$19 -> 42059.923 | L4: =Budget!L4*(Actuals!$K4/Budget!$O4)*Assumptions!$B$19 -> 43435.898 | M4: =Budget!M4*(Actuals!$K4/Budget!$O4)*Assumptions!$B$19 -> 46861.195 | N4: =SUM(B4:M4) -> 483855.02 | O4: =Budget!N4 -> 495820 | P4: =N4-O4 -> -11964.984 | Q4: =IF(O4=0,0,P4/ABS(O4)) -> -0.024131708
A5: Wholesale revenue | B5: =Actuals!B5 -> 51703 | C5: =Actuals!C5 -> 51077 | D5: =Actuals!D5 -> 57405 | E5: =Actuals!E5 -> 58005 | F5: =Actuals!F5 -> 59134 | G5: =Actuals!G5 -> 58749 | H5: =Actuals!H5 -> 59651 | I5: =Actuals!I5 -> 61717 | J5: =Actuals!J5 -> 61476 | K5: =Budget!K5*(Actuals!$K5/Budget!$O5)*Assumptions!$B$19 -> 61792.865 | L5: =Budget!L5*(Actuals!$K5/Budget!$O5)*Assumptions!$B$19 -> 63770.574 | M5: =Budget!M5*(Actuals!$K5/Budget!$O5)*Assumptions!$B$19 -> 68735.884 | N5: =SUM(B5:M5) -> 713216.32 | O5: =Budget!N5 -> 677980 | P5: =N5-O5 -> 35236.323 | Q5: =IF(O5=0,0,P5/ABS(O5)) -> 0.051972511
A6: E-commerce revenue | B6: =Actuals!B6 -> 9929 | C6: =Actuals!C6 -> 9968 | D6: =Actuals!D6 -> 10583 | E6: =Actuals!E6 -> 10919 | F6: =Actuals!F6 -> 11428 | G6: =Actuals!G6 -> 12544 | H6: =Actuals!H6 -> 13338 | I6: =Actuals!I6 -> 13686 | J6: =Actuals!J6 -> 13975 | K6: =Budget!K6*(Actuals!$K6/Budget!$O6)*Assumptions!$B$19 -> 13623.425 | L6: =Budget!L6*(Actuals!$K6/Budget!$O6)*Assumptions!$B$19 -> 14252.341 | M6: =Budget!M6*(Actuals!$K6/Budget!$O6)*Assumptions!$B$19 -> 15574.913 | N6: =SUM(B6:M6) -> 149820.68 | O6: =Budget!N6 -> 161990 | P6: =N6-O6 -> -12169.321 | Q6: =IF(O6=0,0,P6/ABS(O6)) -> -0.075123902
A7: Total Revenue | B7: =SUM(B4:B6) -> 97957 | C7: =SUM(C4:C6) -> 97271 | D7: =SUM(D4:D6) -> 106290 | E7: =SUM(E4:E6) -> 107454 | F7: =SUM(F4:F6) -> 110112 | G7: =SUM(G4:G6) -> 110445 | H7: =SUM(H4:H6) -> 113699 | I7: =SUM(I4:I6) -> 116716 | ... M7: =SUM(M4:M6) -> 131171.99 | N7: =SUM(B7:M7) -> 1346892 | O7: =Budget!N7 -> 1335790 | P7: =N7-O7 -> 11102.018 | Q7: =IF(O7=0,0,P7/ABS(O7)) -> 0.0083112002
A8: COGS - Retail Distribution | B8: =Actuals!B8 -> 23591 | C8: =Actuals!C8 -> 23487 | D8: =Actuals!D8 -> 24782 | E8: =Actuals!E8 -> 24961 | F8: =Actuals!F8 -> 25628 | G8: =Actuals!G8 -> 25367 | H8: =Actuals!H8 -> 26375 | I8: =Actuals!I8 -> 26781 | J8: =Actuals!J8 -> 26743 | K8: =K4*(Actuals!$K8/Actuals!$K4) -> 27248.165 | L8: =L4*(Actuals!$K8/Actuals!$K4) -> 28139.578 | M8: =M4*(Actuals!$K8/Actuals!$K4) -> 30358.628 | N8: =SUM(B8:M8) -> 313461.37 | O8: =Budget!N8 -> 317324.8 | P8: =N8-O8 -> -3863.4288 | Q8: =IF(O8=0,0,P8/ABS(O8)) -> -0.012174998
A9: COGS - Wholesale | B9: =Actuals!B9 -> 39212 | C9: =Actuals!C9 -> 38765 | D9: =Actuals!D9 -> 44427 | E9: =Actuals!E9 -> 44867 | F9: =Actuals!F9 -> 45561 | G9: =Actuals!G9 -> 45358 | H9: =Actuals!H9 -> 46046 | I9: =Actuals!I9 -> 47687 | J9: =Actuals!J9 -> 47498 | K9: =K5*(Actuals!$K9/Actuals!$K5) -> 47563.229 | L9: =L5*(Actuals!$K9/Actuals!$K5) -> 49085.511 | M9: =M5*(Actuals!$K9/Actuals!$K5) -> 52907.412 | N9: =SUM(B9:M9) -> 548977.15 | O9: =Budget!N9 -> 515264.8 | P9: =N9-O9 -> 33712.352 | Q9: =IF(O9=0,0,P9/ABS(O9)) -> 0.065427237
A10: COGS - E-commerce | B10: =Actuals!B10 -> 6790 | C10: =Actuals!C10 -> 6833 | D10: =Actuals!D10 -> 7268 | E10: =Actuals!E10 -> 7488 | F10: =Actuals!F10 -> 7828 | G10: =Actuals!G10 -> 8569 | H10: =Actuals!H10 -> 9122 | I10: =Actuals!I10 -> 9364 | J10: =Actuals!J10 -> 9578 | K10: =K6*(Actuals!$K10/Actuals!$K6) -> 9329.0427 | L10: =L6*(Actuals!$K10/Actuals!$K6) -> 9759.7113 | M10: =M6*(Actuals!$K10/Actuals!$K6) -> 10665.382 | N10: =SUM(B10:M10) -> 102594.14 | O10: =Budget!N10 -> 110153.2 | P10: =N10-O10 -> -7559.0638 | Q10: =IF(O10=0,0,P10/ABS(O10)) -> -0.068623189
A11: Total COGS | B11: =SUM(B8:B10) -> 69593 | C11: =SUM(C8:C10) -> 69085 | D11: =SUM(D8:D10) -> 76477 | E11: =SUM(E8:E10) -> 77316 | F11: =SUM(F8:F10) -> 79017 | G11: =SUM(G8:G10) -> 79294 | H11: =SUM(H8:H10) -> 81543 | I11: =SUM(I8:I10) -> 83832 | ... M11: =SUM(M8:M10) -> 93931.422 | N11: =SUM(B11:M11) -> 965032.66 | O11: =Budget!N11 -> 942742.8 | P11: =N11-O11 -> 22289.859 | Q11: =IF(O11=0,0,P11/ABS(O11)) -> 0.023643627
A12: Gross Profit | B12: =B7-B11 -> 28364 | C12: =C7-C11 -> 28186 | D12: =D7-D11 -> 29813 | E12: =E7-E11 -> 30138 | F12: =F7-F11 -> 31095 | G12: =G7-G11 -> 31151 | H12: =H7-H11 -> 32156 | I12: =I7-I11 -> 32884 | ... M12: =M7-M11 -> 37240.57 | N12: =SUM(B12:M12) -> 381859.36 | O12: =Budget!N12 -> 393047.2 | P12: =N12-O12 -> -11187.841 | Q12: =IF(O12=0,0,P12/ABS(O12)) -> -0.028464371
A13: Gross Margin % | B13: =IF(B7=0,0,B12/B7) -> 0.28955562 | C13: =IF(C7=0,0,C12/C7) -> 0.28976776 | D13: =IF(D7=0,0,D12/D7) -> 0.28048735 | E13: =IF(E7=0,0,E12/E7) -> 0.2804735 | F13: =IF(F7=0,0,F12/F7) -> 0.28239429 | G13: =IF(G7=0,0,G12/G7) -> 0.28204989 | H13: =IF(H7=0,0,H12/H7) -> 0.28281691 | I13: =IF(I7=0,0,I12/I7) -> 0.28174372 | ... N13: =IF(N7=0,0,N12/N7) -> 0.28351149 | O13: =Budget!N13 -> 0.29424326 | P13: =N13-O13 -> -0.01073177
A14: Salaries & Benefits | B14: =Actuals!B14 -> 9484 | C14: =Actuals!C14 -> 9446 | D14: =Actuals!D14 -> 9499 | E14: =Actuals!E14 -> 9482 | F14: =Actuals!F14 -> 9495 | G14: =Actuals!G14 -> 9455 | H14: =Actuals!H14 -> 9795 | I14: =Actuals!I14 -> 9788 | J14: =Actuals!J14 -> 9761 | K14: =Budget!K14*(Actuals!$K14/Budget!$O14) -> 9770.7245 | L14: =Budget!L14*(Actuals!$K14/Budget!$O14) -> 9770.7245 | M14: =Budget!M14*(Actuals!$K14/Budget!$O14) -> 9770.7245 | N14: =SUM(B14:M14) -> 115517.17 | O14: =Budget!N14 -> 112080 | P14: =N14-O14 -> 3437.1736 | Q14: =IF(O14=0,0,P14/ABS(O14)) -> 0.030667145
A15: Marketing & Promotions | B15: =Actuals!B15 -> 2383 | C15: =Actuals!C15 -> 2395 | D15: =Actuals!D15 -> 2575 | E15: =Actuals!E15 -> 2526 | F15: =Actuals!F15 -> 3006 | G15: =Actuals!G15 -> 2978 | H15: =Actuals!H15 -> 3208 | I15: =Actuals!I15 -> 3808 | J15: =Actuals!J15 -> 3810 | K15: =Budget!K15*(Actuals!$K15/Budget!$O15) -> 3481.1739 | L15: =Budget!L15*(Actuals!$K15/Budget!$O15) -> 4061.3696 | M15: =Budget!M15*(Actuals!$K15/Budget!$O15) -> 4641.5652 | N15: =SUM(B15:M15) -> 38873.109 | O15: =Budget!N15 -> 40200 | P15: =N15-O15 -> -1326.8913 | Q15: =IF(O15=0,0,P15/ABS(O15)) -> -0.033007246
A16: Logistics & Distribution | B16: =Actuals!B16 -> 5696 | C16: =Actuals!C16 -> 5554 | D16: =Actuals!D16 -> 5888 | E16: =Actuals!E16 -> 6021 | F16: =Actuals!F16 -> 6133 | G16: =Actuals!G16 -> 6019 | H16: =Actuals!H16 -> 6256 | I16: =Actuals!I16 -> 6346 | J16: =Actuals!J16 -> 6446 | K16: =Budget!K16*(Actuals!$K16/Budget!$O16) -> 6542.5132 | L16: =Budget!L16*(Actuals!$K16/Budget!$O16) -> 6769.234 | M16: =Budget!M16*(Actuals!$K16/Budget!$O16) -> 7309.0453 | N16: =SUM(B16:M16) -> 74979.792 | O16: =Budget!N16 -> 69450 | P16: =N16-O16 -> 5529.7925 | Q16: =IF(O16=0,0,P16/ABS(O16)) -> 0.079622642
A17: Rent & Utilities | B17: =Actuals!B17 -> 2300 | C17: =Actuals!C17 -> 2300 | D17: =Actuals!D17 -> 2300 | E17: =Actuals!E17 -> 2392 | F17: =Actuals!F17 -> 2392 | G17: =Actuals!G17 -> 2392 | H17: =Actuals!H17 -> 2392 | I17: =Actuals!I17 -> 2392 | J17: =Actuals!J17 -> 2392 | K17: =Budget!K17*(Actuals!$K17/Budget!$O17) -> 2361.3333 | L17: =Budget!L17*(Actuals!$K17/Budget!$O17) -> 2361.3333 | M17: =Budget!M17*(Actuals!$K17/Budget!$O17) -> 2361.3333 | N17: =SUM(B17:M17) -> 28336 | O17: =Budget!N17 -> 27600 | P17: =N17-O17 -> 736 | Q17: =IF(O17=0,0,P17/ABS(O17)) -> 0.026666667
A18: Admin & IT | B18: =Actuals!B18 -> 1694 | C18: =Actuals!C18 -> 1703 | D18: =Actuals!D18 -> 1678 | E18: =Actuals!E18 -> 1687 | F18: =Actuals!F18 -> 1706 | G18: =Actuals!G18 -> 1699 | H18: =Actuals!H18 -> 1691 | I18: =Actuals!I18 -> 1705 | J18: =Actuals!J18 -> 1706 | K18: =Budget!K18*(Actuals!$K18/Budget!$O18) -> 1696.5556 | L18: =Budget!L18*(Actuals!$K18/Budget!$O18) -> 1696.5556 | M18: =Budget!M18*(Actuals!$K18/Budget!$O18) -> 1696.5556 | N18: =SUM(B18:M18) -> 20358.667 | O18: =Budget!N18 -> 21600 | P18: =N18-O18 -> -1241.3333 | Q18: =IF(O18=0,0,P18/ABS(O18)) -> -0.057469136
A19: Total Operating Expenses | B19: =SUM(B14:B18) -> 21557 | C19: =SUM(C14:C18) -> 21398 | D19: =SUM(D14:D18) -> 21940 | E19: =SUM(E14:E18) -> 22108 | F19: =SUM(F14:F18) -> 22732 | G19: =SUM(G14:G18) -> 22543 | H19: =SUM(H14:H18) -> 23342 | I19: =SUM(I14:I18) -> 24039 | ... M19: =SUM(M14:M18) -> 25779.224 | N19: =SUM(B19:M19) -> 278064.74 | O19: =Budget!N19 -> 270930 | P19: =N19-O19 -> 7134.7414 | Q19: =IF(O19=0,0,P19/ABS(O19)) -> 0.026334261
A20: EBITDA | B20: =B12-B19 -> 6807 | C20: =C12-C19 -> 6788 | D20: =D12-D19 -> 7873 | E20: =E12-E19 -> 8030 | F20: =F12-F19 -> 8363 | G20: =G12-G19 -> 8608 | H20: =H12-H19 -> 8814 | I20: =I12-I19 -> 8845 | ... M20: =M12-M19 -> 11461.347 | N20: =SUM(B20:M20) -> 103794.62 | O20: =Budget!N20 -> 122117.2 | P20: =N20-O20 -> -18322.583 | Q20: =IF(O20=0,0,P20/ABS(O20)) -> -0.15004097
A21: EBITDA Margin % | B21: =IF(B7=0,0,B20/B7) -> 0.069489674 | C21: =IF(C7=0,0,C20/C7) -> 0.069784417 | D21: =IF(D7=0,0,D20/D7) -> 0.074070938 | E21: =IF(E7=0,0,E20/E7) -> 0.074729652 | F21: =IF(F7=0,0,F20/F7) -> 0.075949942 | G21: =IF(G7=0,0,G20/G7) -> 0.077939246 | H21: =IF(H7=0,0,H20/H7) -> 0.077520471 | I21: =IF(I7=0,0,I20/I7) -> 0.075782241 | ... N21: =IF(N7=0,0,N20/N7) -> 0.077062315 | O21: =Budget!N21 -> 0.09141946 | P21: =N21-O21 -> -0.014357144
A22: Depreciation | B22: =Actuals!B22 -> 1600 | C22: =Actuals!C22 -> 1600 | D22: =Actuals!D22 -> 1600 | E22: =Actuals!E22 -> 1600 | F22: =Actuals!F22 -> 1600 | G22: =Actuals!G22 -> 1600 | H22: =Actuals!H22 -> 1600 | I22: =Actuals!I22 -> 1600 | J22: =Actuals!J22 -> 1600 | K22: =Budget!K22 -> 1600 | L22: =Budget!L22 -> 1600 | M22: =Budget!M22 -> 1600 | N22: =SUM(B22:M22) -> 19200 | O22: =Budget!N22 -> 19200 | P22: =N22-O22 -> 0 | Q22: =IF(O22=0,0,P22/ABS(O22)) -> 0
A23: Operating Profit (EBIT) | B23: =B20-B22 -> 5207 | C23: =C20-C22 -> 5188 | D23: =D20-D22 -> 6273 | E23: =E20-E22 -> 6430 | F23: =F20-F22 -> 6763 | G23: =G20-G22 -> 7008 | H23: =H20-H22 -> 7214 | I23: =I20-I22 -> 7245 | ... M23: =M20-M22 -> 9861.3465 | N23: =SUM(B23:M23) -> 84594.617 | O23: =Budget!N23 -> 102917.2 | P23: =N23-O23 -> -18322.583 | Q23: =IF(O23=0,0,P23/ABS(O23)) -> -0.17803227
A24: Finance Costs | B24: =Actuals!B24 -> 1545 | C24: =Actuals!C24 -> 1524 | D24: =Actuals!D24 -> 1504 | E24: =Actuals!E24 -> 1483 | F24: =Actuals!F24 -> 1463 | G24: =Actuals!G24 -> 1442 | H24: =Actuals!H24 -> 1421 | I24: =Actuals!I24 -> 1401 | J24: =Actuals!J24 -> 1380 | K24: =Budget!K24 -> 1320 | L24: =Budget!L24 -> 1300 | M24: =Budget!M24 -> 1280 | N24: =SUM(B24:M24) -> 17063 | O24: =Budget!N24 -> 16680 | P24: =N24-O24 -> 383 | Q24: =IF(O24=0,0,P24/ABS(O24)) -> 0.022961631
A25: Profit Before Tax | B25: =B23-B24 -> 3662 | C25: =C23-C24 -> 3664 | D25: =D23-D24 -> 4769 | E25: =E23-E24 -> 4947 | F25: =F23-F24 -> 5300 | G25: =G23-G24 -> 5566 | H25: =H23-H24 -> 5793 | I25: =I23-I24 -> 5844 | ... M25: =M23-M24 -> 8581.3465 | N25: =SUM(B25:M25) -> 67531.617 | O25: =Budget!N25 -> 86237.2 | P25: =N25-O25 -> -18705.583 | Q25: =IF(O25=0,0,P25/ABS(O25)) -> -0.21690851
A26: Income Tax | B26: =MAX(0,B25)*Assumptions!$B$15 -> 1098.6 | C26: =MAX(0,C25)*Assumptions!$B$15 -> 1099.2 | D26: =MAX(0,D25)*Assumptions!$B$15 -> 1430.7 | E26: =MAX(0,E25)*Assumptions!$B$15 -> 1484.1 | F26: =MAX(0,F25)*Assumptions!$B$15 -> 1590 | G26: =MAX(0,G25)*Assumptions!$B$15 -> 1669.8 | H26: =MAX(0,H25)*Assumptions!$B$15 -> 1737.9 | I26: =MAX(0,I25)*Assumptions!$B$15 -> 1753.2 | ... M26: =MAX(0,M25)*Assumptions!$B$15 -> 2574.404 | N26: =SUM(B26:M26) -> 20259.485 | O26: =Budget!N26 -> 25871.16 | P26: =N26-O26 -> -5611.6748 | Q26: =IF(O26=0,0,P26/ABS(O26)) -> -0.21690851
A27: Net Profit | B27: =B25-B26 -> 2563.4 | C27: =C25-C26 -> 2564.8 | D27: =D25-D26 -> 3338.3 | E27: =E25-E26 -> 3462.9 | F27: =F25-F26 -> 3710 | G27: =G25-G26 -> 3896.2 | H27: =H25-H26 -> 4055.1 | I27: =I25-I26 -> 4090.8 | ... M27: =M25-M26 -> 6006.9426 | N27: =SUM(B27:M27) -> 47272.132 | O27: =Budget!N27 -> 60366.04 | P27: =N27-O27 -> -13093.908 | Q27: =IF(O27=0,0,P27/ABS(O27)) -> -0.21690851
A29: Oct-Dec (brown headers) are forecast; see Assumptions for method. Margin variance (rows 13, 21) is in percentage points.
