Workbook

Sheet README
A1: HR Workforce & Attrition Analytics
A3: Business scenario | B3: A mid-sized Kenyan company has rising staff turnover. HR needs to know the attrition rate, which departments and tenure bands lose people, why they leave, and what turnover costs.
A5: Sheets | B5: Assumptions: as-of date, 12-month window, replacement-cost multiplier, attrition and absenteeism targets.
B6: Employees: 300 synthetic staff records (inputs) plus formula columns for status, tenure, 12-month leaver flag and replacement cost.
B7: Dashboard: headcount, attrition rate, regrettable losses, cost of turnover, tables by department, tenure band and exit reason, and charts.
A9: Colour legend | B9: Blue text on yellow = editable input (Assumptions sheet).
B10: Blue header on Data sheet = raw input columns; green header = formula columns (do not overwrite).
B11: Black text = formula. Everything on the Dashboard recalculates when Assumptions or Data change.
A13: Data note | B13: All data is SYNTHETIC, generated for portfolio demonstration. Targets and thresholds are illustrative. Not client data.
A15: Skills demonstrated | B15: HR metrics (attrition, tenure, absenteeism)
B16: Date logic and helper flags
B17: AVERAGEIFS / COUNTIFS / SUMIFS
B18: Cost-of-turnover modelling
B19: Dashboard design

Sheet Dashboard
A1: HR Workforce & Attrition Dashboard
A2: Synthetic data | KES | 12-month window ending on the as-of date
A4: Key metrics
A5: Active headcount | B5: =COUNTIFS(Employees!$K$2:$K$301,"Active") -> 224
A6: Headcount at window start | B6: =SUM(Employees!$O$2:$O$301) -> 260
A7: Leavers in last 12 months | B7: =SUM(Employees!$P$2:$P$301) -> 62
A8: Annual attrition rate | B8: =IF((B5+B6)=0,0,B7/AVERAGE(B5,B6)) -> 0.25619835
A9: Attrition vs target | B9: =IF(B8<=Assumptions!$B$8,"Within target","Above target") -> Above target
A10: Regrettable leavers | B10: =SUM(Employees!$R$2:$R$301) -> 23
A11: Replacement cost of leavers (KES) | B11: =SUM(Employees!$Q$2:$Q$301) -> 34398000
A12: Annual payroll, active staff (KES) | B12: =SUMIFS(Employees!$N$2:$N$301,Employees!$K$2:$K$301,"Active") -> 239040000
A13: Avg days absent, active staff | B13: =AVERAGEIFS(Employees!$I$2:$I$301,Employees!$K$2:$K$301,"Active") -> 5.7008929
A15: Insights (auto-updating)
A16: Highest-attrition department | B16: =INDEX(A22:A27,MATCH(MAX(E22:E27),E22:E27,0)) -> IT
A17: Top exit reason | B17: =INDEX(A40:A46,MATCH(MAX(B40:B46),B40:B46,0)) -> Better pay elsewhere
A18: Share of leavers with under 1 yr tenure | B18: =D32 -> 0.12903226
A20: By department
A21: Department | B21: Active now | C21: Active at start | D21: Leavers 12m | E21: Attrition % | F21: Avg days absent | G21: Avg monthly salary (KES) | H21: Replacement cost (KES) | I21: Regrettable leavers | J21: vs target
A22: Sales | B22: =COUNTIFS(Employees!$B$2:$B$301,$A22,Employees!$K$2:$K$301,"Active") -> 50 | C22: =SUMIFS(Employees!$O$2:$O$301,Employees!$B$2:$B$301,$A22) -> 59 | D22: =SUMIFS(Employees!$P$2:$P$301,Employees!$B$2:$B$301,$A22) -> 16 | E22: =IF((B22+C22)=0,0,D22/AVERAGE(B22,C22)) -> 0.29357798 | F22: =IFERROR(AVERAGEIFS(Employees!$I$2:$I$301,Employees!$B$2:$B$301,$A22,Employees!$K$2:$K$301,"Active"),0) -> 4.88 | G22: =IFERROR(AVERAGEIFS(Employees!$H$2:$H$301,Employees!$B$2:$B$301,$A22,Employees!$K$2:$K$301,"Active"),0) -> 84880 | H22: =SUMIFS(Employees!$Q$2:$Q$301,Employees!$B$2:$B$301,$A22) -> 9540000 | I22: =SUMIFS(Employees!$R$2:$R$301,Employees!$B$2:$B$301,$A22) -> 9 | J22: =IF(E22<=Assumptions!$B$8,"OK","Above target") -> Above target
A23: Operations | B23: =COUNTIFS(Employees!$B$2:$B$301,$A23,Employees!$K$2:$K$301,"Active") -> 48 | C23: =SUMIFS(Employees!$O$2:$O$301,Employees!$B$2:$B$301,$A23) -> 53 | D23: =SUMIFS(Employees!$P$2:$P$301,Employees!$B$2:$B$301,$A23) -> 9 | E23: =IF((B23+C23)=0,0,D23/AVERAGE(B23,C23)) -> 0.17821782 | F23: =IFERROR(AVERAGEIFS(Employees!$I$2:$I$301,Employees!$B$2:$B$301,$A23,Employees!$K$2:$K$301,"Active"),0) -> 4.7291667 | G23: =IFERROR(AVERAGEIFS(Employees!$H$2:$H$301,Employees!$B$2:$B$301,$A23,Employees!$K$2:$K$301,"Active"),0) -> 83583.333 | H23: =SUMIFS(Employees!$Q$2:$Q$301,Employees!$B$2:$B$301,$A23) -> 4260000 | I23: =SUMIFS(Employees!$R$2:$R$301,Employees!$B$2:$B$301,$A23) -> 1 | J23: =IF(E23<=Assumptions!$B$8,"OK","Above target") -> Above target
A24: Finance | B24: =COUNTIFS(Employees!$B$2:$B$301,$A24,Employees!$K$2:$K$301,"Active") -> 29 | C24: =SUMIFS(Employees!$O$2:$O$301,Employees!$B$2:$B$301,$A24) -> 30 | D24: =SUMIFS(Employees!$P$2:$P$301,Employees!$B$2:$B$301,$A24) -> 4 | E24: =IF((B24+C24)=0,0,D24/AVERAGE(B24,C24)) -> 0.13559322 | F24: =IFERROR(AVERAGEIFS(Employees!$I$2:$I$301,Employees!$B$2:$B$301,$A24,Employees!$K$2:$K$301,"Active"),0) -> 5.6896552 | G24: =IFERROR(AVERAGEIFS(Employees!$H$2:$H$301,Employees!$B$2:$B$301,$A24,Employees!$K$2:$K$301,"Active"),0) -> 96655.172 | H24: =SUMIFS(Employees!$Q$2:$Q$301,Employees!$B$2:$B$301,$A24) -> 1698000 | I24: =SUMIFS(Employees!$R$2:$R$301,Employees!$B$2:$B$301,$A24) -> 1 | J24: =IF(E24<=Assumptions!$B$8,"OK","Above target") -> OK
A25: IT | B25: =COUNTIFS(Employees!$B$2:$B$301,$A25,Employees!$K$2:$K$301,"Active") -> 22 | C25: =SUMIFS(Employees!$O$2:$O$301,Employees!$B$2:$B$301,$A25) -> 35 | D25: =SUMIFS(Employees!$P$2:$P$301,Employees!$B$2:$B$301,$A25) -> 15 | E25: =IF((B25+C25)=0,0,D25/AVERAGE(B25,C25)) -> 0.52631579 | F25: =IFERROR(AVERAGEIFS(Employees!$I$2:$I$301,Employees!$B$2:$B$301,$A25,Employees!$K$2:$K$301,"Active"),0) -> 4.5454545 | G25: =IFERROR(AVERAGEIFS(Employees!$H$2:$H$301,Employees!$B$2:$B$301,$A25,Employees!$K$2:$K$301,"Active"),0) -> 91272.727 | H25: =SUMIFS(Employees!$Q$2:$Q$301,Employees!$B$2:$B$301,$A25) -> 9456000 | I25: =SUMIFS(Employees!$R$2:$R$301,Employees!$B$2:$B$301,$A25) -> 7 | J25: =IF(E25<=Assumptions!$B$8,"OK","Above target") -> Above target
A26: HR | B26: =COUNTIFS(Employees!$B$2:$B$301,$A26,Employees!$K$2:$K$301,"Active") -> 14 | C26: =SUMIFS(Employees!$O$2:$O$301,Employees!$B$2:$B$301,$A26) -> 15 | D26: =SUMIFS(Employees!$P$2:$P$301,Employees!$B$2:$B$301,$A26) -> 1 | E26: =IF((B26+C26)=0,0,D26/AVERAGE(B26,C26)) -> 0.068965517 | F26: =IFERROR(AVERAGEIFS(Employees!$I$2:$I$301,Employees!$B$2:$B$301,$A26,Employees!$K$2:$K$301,"Active"),0) -> 5.1428571 | G26: =IFERROR(AVERAGEIFS(Employees!$H$2:$H$301,Employees!$B$2:$B$301,$A26,Employees!$K$2:$K$301,"Active"),0) -> 99928.571 | H26: =SUMIFS(Employees!$Q$2:$Q$301,Employees!$B$2:$B$301,$A26) -> 996000 | I26: =SUMIFS(Employees!$R$2:$R$301,Employees!$B$2:$B$301,$A26) -> 1 | J26: =IF(E26<=Assumptions!$B$8,"OK","Above target") -> OK
A27: Customer Service | B27: =COUNTIFS(Employees!$B$2:$B$301,$A27,Employees!$K$2:$K$301,"Active") -> 61 | C27: =SUMIFS(Employees!$O$2:$O$301,Employees!$B$2:$B$301,$A27) -> 68 | D27: =SUMIFS(Employees!$P$2:$P$301,Employees!$B$2:$B$301,$A27) -> 17 | E27: =IF((B27+C27)=0,0,D27/AVERAGE(B27,C27)) -> 0.26356589 | F27: =IFERROR(AVERAGEIFS(Employees!$I$2:$I$301,Employees!$B$2:$B$301,$A27,Employees!$K$2:$K$301,"Active"),0) -> 7.6885246 | G27: =IFERROR(AVERAGEIFS(Employees!$H$2:$H$301,Employees!$B$2:$B$301,$A27,Employees!$K$2:$K$301,"Active"),0) -> 89409.836 | H27: =SUMIFS(Employees!$Q$2:$Q$301,Employees!$B$2:$B$301,$A27) -> 8448000 | I27: =SUMIFS(Employees!$R$2:$R$301,Employees!$B$2:$B$301,$A27) -> 4 | J27: =IF(E27<=Assumptions!$B$8,"OK","Above target") -> Above target
A30: Leavers by tenure band
A31: Tenure band | B31: Active now | C31: Leavers 12m | D31: Share of leavers
A32: Under 1 yr | B32: =COUNTIFS(Employees!$M$2:$M$301,$A32,Employees!$K$2:$K$301,"Active") -> 20 | C32: =COUNTIFS(Employees!$M$2:$M$301,$A32,Employees!$P$2:$P$301,1) -> 8 | D32: =IF(SUM(C$32:C$35)=0,0,C32/SUM(C$32:C$35)) -> 0.12903226
A33: 1 to 3 yrs | B33: =COUNTIFS(Employees!$M$2:$M$301,$A33,Employees!$K$2:$K$301,"Active") -> 39 | C33: =COUNTIFS(Employees!$M$2:$M$301,$A33,Employees!$P$2:$P$301,1) -> 10 | D33: =IF(SUM(C$32:C$35)=0,0,C33/SUM(C$32:C$35)) -> 0.16129032
A34: 3 to 5 yrs | B34: =COUNTIFS(Employees!$M$2:$M$301,$A34,Employees!$K$2:$K$301,"Active") -> 38 | C34: =COUNTIFS(Employees!$M$2:$M$301,$A34,Employees!$P$2:$P$301,1) -> 7 | D34: =IF(SUM(C$32:C$35)=0,0,C34/SUM(C$32:C$35)) -> 0.11290323
A35: 5+ yrs | B35: =COUNTIFS(Employees!$M$2:$M$301,$A35,Employees!$K$2:$K$301,"Active") -> 127 | C35: =COUNTIFS(Employees!$M$2:$M$301,$A35,Employees!$P$2:$P$301,1) -> 37 | D35: =IF(SUM(C$32:C$35)=0,0,C35/SUM(C$32:C$35)) -> 0.59677419
A38: Exit reasons (last 12 months)
A39: Reason | B39: Leavers | C39: Share
A40: Better pay elsewhere | B40: =COUNTIFS(Employees!$G$2:$G$301,$A40,Employees!$P$2:$P$301,1) -> 18 | C40: =IF(SUM(B$40:B$46)=0,0,B40/SUM(B$40:B$46)) -> 0.29032258
A41: Career growth | B41: =COUNTIFS(Employees!$G$2:$G$301,$A41,Employees!$P$2:$P$301,1) -> 16 | C41: =IF(SUM(B$40:B$46)=0,0,B41/SUM(B$40:B$46)) -> 0.25806452
A42: Relocation | B42: =COUNTIFS(Employees!$G$2:$G$301,$A42,Employees!$P$2:$P$301,1) -> 5 | C42: =IF(SUM(B$40:B$46)=0,0,B42/SUM(B$40:B$46)) -> 0.080645161
A43: Personal / family | B43: =COUNTIFS(Employees!$G$2:$G$301,$A43,Employees!$P$2:$P$301,1) -> 9 | C43: =IF(SUM(B$40:B$46)=0,0,B43/SUM(B$40:B$46)) -> 0.14516129
A44: Poor management | B44: =COUNTIFS(Employees!$G$2:$G$301,$A44,Employees!$P$2:$P$301,1) -> 6 | C44: =IF(SUM(B$40:B$46)=0,0,B44/SUM(B$40:B$46)) -> 0.096774194
A45: Contract ended | B45: =COUNTIFS(Employees!$G$2:$G$301,$A45,Employees!$P$2:$P$301,1) -> 7 | C45: =IF(SUM(B$40:B$46)=0,0,B45/SUM(B$40:B$46)) -> 0.11290323
A46: Dismissal | B46: =COUNTIFS(Employees!$G$2:$G$301,$A46,Employees!$P$2:$P$301,1) -> 1 | C46: =IF(SUM(B$40:B$46)=0,0,B46/SUM(B$40:B$46)) -> 0.016129032

Sheet Assumptions
A1: Assumptions (edit the yellow cells)
A4: Parameter | B4: Value | C4: Note
A5: As-of date | B5: 46295 | C5: Reporting date for headcount and tenure.
A6: 12-month window start | B6: =B5-365 -> 45930 | C6: Formula: as-of date minus 365 days.
A7: Replacement cost (% of annual salary) | B7: 0.5 | C7: Illustrative: recruitment, onboarding and lost productivity.
A8: Target annual attrition | B8: 0.15 | C8: Illustrative target.
A9: Absenteeism target (days / person / year) | B9: 6 | C9: Illustrative target.
A10: Regrettable-loss rating threshold (>=) | B10: 4 | C10: Leavers rated at or above this count as regrettable.

Sheet Employees
A1: Employee ID | B1: Department | C1: Level | D1: Gender | E1: Hire date | F1: Exit date | G1: Exit reason | H1: Monthly salary (KES) | I1: Days absent (12m) | J1: Performance rating (1-5) | K1: Status | L1: Tenure (years) | M1: Tenure band | N1: Annual salary (KES) | O1: Active at window start | P1: Left in window | Q1: Replacement cost (KES) | R1: Regrettable loss
A2: EMP2001 | B2: Customer Service | C2: Junior | D2: M | E2: 42198 | H2: 57000 | I2: 11 | J2: 4 | K2: =IF(F2="","Active","Left") -> Active | L2: =ROUND((IF(F2="",Assumptions!$B$5,F2)-E2)/365.25,1) -> 11.2 | M2: =IF(L2<1,"Under 1 yr",IF(L2<3,"1 to 3 yrs",IF(L2<5,"3 to 5 yrs","5+ yrs"))) -> 5+ yrs | N2: =H2*12 -> 684000 | O2: =IF(AND(E2<Assumptions!$B$6,OR(F2="",F2>=Assumptions!$B$6)),1,0) -> 1 | P2: =IF(F2="",0,IF(AND(F2>=Assumptions!$B$6,F2<=Assumptions!$B$5),1,0)) -> 0 | Q2: =P2*N2*Assumptions!$B$7 -> 0 | R2: =IF(AND(P2=1,J2>=Assumptions!$B$10),1,0) -> 0
A3: EMP2002 | B3: Sales | C3: Junior | D3: M | E3: 42411 | H3: 52000 | I3: 7 | J3: 4 | K3: =IF(F3="","Active","Left") -> Active | L3: =ROUND((IF(F3="",Assumptions!$B$5,F3)-E3)/365.25,1) -> 10.6 | M3: =IF(L3<1,"Under 1 yr",IF(L3<3,"1 to 3 yrs",IF(L3<5,"3 to 5 yrs","5+ yrs"))) -> 5+ yrs | N3: =H3*12 -> 624000 | O3: =IF(AND(E3<Assumptions!$B$6,OR(F3="",F3>=Assumptions!$B$6)),1,0) -> 1 | P3: =IF(F3="",0,IF(AND(F3>=Assumptions!$B$6,F3<=Assumptions!$B$5),1,0)) -> 0 | Q3: =P3*N3*Assumptions!$B$7 -> 0 | R3: =IF(AND(P3=1,J3>=Assumptions!$B$10),1,0) -> 0
A4: EMP2003 | B4: Sales | C4: Senior | D4: F | E4: 44167 | H4: 124000 | I4: 0 | J4: 4 | K4: =IF(F4="","Active","Left") -> Active | L4: =ROUND((IF(F4="",Assumptions!$B$5,F4)-E4)/365.25,1) -> 5.8 | M4: =IF(L4<1,"Under 1 yr",IF(L4<3,"1 to 3 yrs",IF(L4<5,"3 to 5 yrs","5+ yrs"))) -> 5+ yrs | N4: =H4*12 -> 1488000 | O4: =IF(AND(E4<Assumptions!$B$6,OR(F4="",F4>=Assumptions!$B$6)),1,0) -> 1 | P4: =IF(F4="",0,IF(AND(F4>=Assumptions!$B$6,F4<=Assumptions!$B$5),1,0)) -> 0 | Q4: =P4*N4*Assumptions!$B$7 -> 0 | R4: =IF(AND(P4=1,J4>=Assumptions!$B$10),1,0) -> 0
A5: EMP2004 | B5: IT | C5: Junior | D5: F | E5: 45225 | H5: 55000 | I5: 1 | J5: 3 | K5: =IF(F5="","Active","Left") -> Active | L5: =ROUND((IF(F5="",Assumptions!$B$5,F5)-E5)/365.25,1) -> 2.9 | M5: =IF(L5<1,"Under 1 yr",IF(L5<3,"1 to 3 yrs",IF(L5<5,"3 to 5 yrs","5+ yrs"))) -> 1 to 3 yrs | N5: =H5*12 -> 660000 | O5: =IF(AND(E5<Assumptions!$B$6,OR(F5="",F5>=Assumptions!$B$6)),1,0) -> 1 | P5: =IF(F5="",0,IF(AND(F5>=Assumptions!$B$6,F5<=Assumptions!$B$5),1,0)) -> 0 | Q5: =P5*N5*Assumptions!$B$7 -> 0 | R5: =IF(AND(P5=1,J5>=Assumptions!$B$10),1,0) -> 0
A6: EMP2005 | B6: Operations | C6: Officer | D6: M | E6: 45543 | F6: 46202 | G6: Contract ended | H6: 86000 | I6: 8 | J6: 3 | K6: =IF(F6="","Active","Left") -> Left | L6: =ROUND((IF(F6="",Assumptions!$B$5,F6)-E6)/365.25,1) -> 1.8 | M6: =IF(L6<1,"Under 1 yr",IF(L6<3,"1 to 3 yrs",IF(L6<5,"3 to 5 yrs","5+ yrs"))) -> 1 to 3 yrs | N6: =H6*12 -> 1032000 | O6: =IF(AND(E6<Assumptions!$B$6,OR(F6="",F6>=Assumptions!$B$6)),1,0) -> 1 | P6: =IF(F6="",0,IF(AND(F6>=Assumptions!$B$6,F6<=Assumptions!$B$5),1,0)) -> 1 | Q6: =P6*N6*Assumptions!$B$7 -> 516000 | R6: =IF(AND(P6=1,J6>=Assumptions!$B$10),1,0) -> 0
A7: EMP2006 | B7: Customer Service | C7: Junior | D7: M | E7: 45066 | F7: 45755 | G7: Personal / family | H7: 52000 | I7: 6 | J7: 4 | K7: =IF(F7="","Active","Left") -> Left | L7: =ROUND((IF(F7="",Assumptions!$B$5,F7)-E7)/365.25,1) -> 1.9 | M7: =IF(L7<1,"Under 1 yr",IF(L7<3,"1 to 3 yrs",IF(L7<5,"3 to 5 yrs","5+ yrs"))) -> 1 to 3 yrs | N7: =H7*12 -> 624000 | O7: =IF(AND(E7<Assumptions!$B$6,OR(F7="",F7>=Assumptions!$B$6)),1,0) -> 0 | P7: =IF(F7="",0,IF(AND(F7>=Assumptions!$B$6,F7<=Assumptions!$B$5),1,0)) -> 0 | Q7: =P7*N7*Assumptions!$B$7 -> 0 | R7: =IF(AND(P7=1,J7>=Assumptions!$B$10),1,0) -> 0
A8: EMP2007 | B8: Customer Service | C8: Officer | D8: F | E8: 42746 | H8: 87000 | I8: 8 | J8: 3 | K8: =IF(F8="","Active","Left") -> Active | L8: =ROUND((IF(F8="",Assumptions!$B$5,F8)-E8)/365.25,1) -> 9.7 | M8: =IF(L8<1,"Under 1 yr",IF(L8<3,"1 to 3 yrs",IF(L8<5,"3 to 5 yrs","5+ yrs"))) -> 5+ yrs | N8: =H8*12 -> 1044000 | O8: =IF(AND(E8<Assumptions!$B$6,OR(F8="",F8>=Assumptions!$B$6)),1,0) -> 1 | P8: =IF(F8="",0,IF(AND(F8>=Assumptions!$B$6,F8<=Assumptions!$B$5),1,0)) -> 0 | Q8: =P8*N8*Assumptions!$B$7 -> 0 | R8: =IF(AND(P8=1,J8>=Assumptions!$B$10),1,0) -> 0
A9: EMP2008 | B9: Operations | C9: Junior | D9: F | E9: 43589 | H9: 46000 | I9: 3 | J9: 3 | K9: =IF(F9="","Active","Left") -> Active | L9: =ROUND((IF(F9="",Assumptions!$B$5,F9)-E9)/365.25,1) -> 7.4 | M9: =IF(L9<1,"Under 1 yr",IF(L9<3,"1 to 3 yrs",IF(L9<5,"3 to 5 yrs","5+ yrs"))) -> 5+ yrs | N9: =H9*12 -> 552000 | O9: =IF(AND(E9<Assumptions!$B$6,OR(F9="",F9>=Assumptions!$B$6)),1,0) -> 1 | P9: =IF(F9="",0,IF(AND(F9>=Assumptions!$B$6,F9<=Assumptions!$B$5),1,0)) -> 0 | Q9: =P9*N9*Assumptions!$B$7 -> 0 | R9: =IF(AND(P9=1,J9>=Assumptions!$B$10),1,0) -> 0
A10: EMP2009 | B10: Operations | C10: Junior | D10: F | E10: 42307 | F10: 45998 | G10: Poor management | H10: 55000 | I10: 4 | J10: 2 | K10: =IF(F10="","Active","Left") -> Left | L10: =ROUND((IF(F10="",Assumptions!$B$5,F10)-E10)/365.25,1) -> 10.1 | M10: =IF(L10<1,"Under 1 yr",IF(L10<3,"1 to 3 yrs",IF(L10<5,"3 to 5 yrs","5+ yrs"))) -> 5+ yrs | N10: =H10*12 -> 660000 | O10: =IF(AND(E10<Assumptions!$B$6,OR(F10="",F10>=Assumptions!$B$6)),1,0) -> 1 | P10: =IF(F10="",0,IF(AND(F10>=Assumptions!$B$6,F10<=Assumptions!$B$5),1,0)) -> 1 | Q10: =P10*N10*Assumptions!$B$7 -> 330000 | R10: =IF(AND(P10=1,J10>=Assumptions!$B$10),1,0) -> 0
A11: EMP2010 | B11: Operations | C11: Senior | D11: F | E11: 45778 | F11: 45991 | G11: Career growth | H11: 177000 | I11: 0 | J11: 3 | K11: =IF(F11="","Active","Left") -> Left | L11: =ROUND((IF(F11="",Assumptions!$B$5,F11)-E11)/365.25,1) -> 0.6 | M11: =IF(L11<1,"Under 1 yr",IF(L11<3,"1 to 3 yrs",IF(L11<5,"3 to 5 yrs","5+ yrs"))) -> Under 1 yr | N11: =H11*12 -> 2124000 | O11: =IF(AND(E11<Assumptions!$B$6,OR(F11="",F11>=Assumptions!$B$6)),1,0) -> 1 | P11: =IF(F11="",0,IF(AND(F11>=Assumptions!$B$6,F11<=Assumptions!$B$5),1,0)) -> 1 | Q11: =P11*N11*Assumptions!$B$7 -> 1062000 | R11: =IF(AND(P11=1,J11>=Assumptions!$B$10),1,0) -> 0
A12: EMP2011 | B12: Customer Service | C12: Officer | D12: M | E12: 45880 | H12: 105000 | I12: 4 | J12: 5 | K12: =IF(F12="","Active","Left") -> Active | L12: =ROUND((IF(F12="",Assumptions!$B$5,F12)-E12)/365.25,1) -> 1.1 | M12: =IF(L12<1,"Under 1 yr",IF(L12<3,"1 to 3 yrs",IF(L12<5,"3 to 5 yrs","5+ yrs"))) -> 1 to 3 yrs | N12: =H12*12 -> 1260000 | O12: =IF(AND(E12<Assumptions!$B$6,OR(F12="",F12>=Assumptions!$B$6)),1,0) -> 1 | P12: =IF(F12="",0,IF(AND(F12>=Assumptions!$B$6,F12<=Assumptions!$B$5),1,0)) -> 0 | Q12: =P12*N12*Assumptions!$B$7 -> 0 | R12: =IF(AND(P12=1,J12>=Assumptions!$B$10),1,0) -> 0
A13: EMP2012 | B13: Sales | C13: Officer | D13: M | E13: 42529 | H13: 104000 | I13: 9 | J13: 4 | K13: =IF(F13="","Active","Left") -> Active | L13: =ROUND((IF(F13="",Assumptions!$B$5,F13)-E13)/365.25,1) -> 10.3 | M13: =IF(L13<1,"Under 1 yr",IF(L13<3,"1 to 3 yrs",IF(L13<5,"3 to 5 yrs","5+ yrs"))) -> 5+ yrs | N13: =H13*12 -> 1248000 | O13: =IF(AND(E13<Assumptions!$B$6,OR(F13="",F13>=Assumptions!$B$6)),1,0) -> 1 | P13: =IF(F13="",0,IF(AND(F13>=Assumptions!$B$6,F13<=Assumptions!$B$5),1,0)) -> 0 | Q13: =P13*N13*Assumptions!$B$7 -> 0 | R13: =IF(AND(P13=1,J13>=Assumptions!$B$10),1,0) -> 0
A14: EMP2013 | B14: Sales | C14: Junior | D14: F | E14: 43566 | H14: 41000 | I14: 1 | J14: 2 | K14: =IF(F14="","Active","Left") -> Active | L14: =ROUND((IF(F14="",Assumptions!$B$5,F14)-E14)/365.25,1) -> 7.5 | M14: =IF(L14<1,"Under 1 yr",IF(L14<3,"1 to 3 yrs",IF(L14<5,"3 to 5 yrs","5+ yrs"))) -> 5+ yrs | N14: =H14*12 -> 492000 | O14: =IF(AND(E14<Assumptions!$B$6,OR(F14="",F14>=Assumptions!$B$6)),1,0) -> 1 | P14: =IF(F14="",0,IF(AND(F14>=Assumptions!$B$6,F14<=Assumptions!$B$5),1,0)) -> 0 | Q14: =P14*N14*Assumptions!$B$7 -> 0 | R14: =IF(AND(P14=1,J14>=Assumptions!$B$10),1,0) -> 0
A15: EMP2014 | B15: Operations | C15: Junior | D15: F | E15: 45854 | H15: 38000 | I15: 4 | J15: 1 | K15: =IF(F15="","Active","Left") -> Active | L15: =ROUND((IF(F15="",Assumptions!$B$5,F15)-E15)/365.25,1) -> 1.2 | M15: =IF(L15<1,"Under 1 yr",IF(L15<3,"1 to 3 yrs",IF(L15<5,"3 to 5 yrs","5+ yrs"))) -> 1 to 3 yrs | N15: =H15*12 -> 456000 | O15: =IF(AND(E15<Assumptions!$B$6,OR(F15="",F15>=Assumptions!$B$6)),1,0) -> 1 | P15: =IF(F15="",0,IF(AND(F15>=Assumptions!$B$6,F15<=Assumptions!$B$5),1,0)) -> 0 | Q15: =P15*N15*Assumptions!$B$7 -> 0 | R15: =IF(AND(P15=1,J15>=Assumptions!$B$10),1,0) -> 0
A16: EMP2015 | B16: Operations | C16: Senior | D16: M | E16: 42275 | H16: 158000 | I16: 9 | J16: 3 | K16: =IF(F16="","Active","Left") -> Active | L16: =ROUND((IF(F16="",Assumptions!$B$5,F16)-E16)/365.25,1) -> 11 | M16: =IF(L16<1,"Under 1 yr",IF(L16<3,"1 to 3 yrs",IF(L16<5,"3 to 5 yrs","5+ yrs"))) -> 5+ yrs | N16: =H16*12 -> 1896000 | O16: =IF(AND(E16<Assumptions!$B$6,OR(F16="",F16>=Assumptions!$B$6)),1,0) -> 1 | P16: =IF(F16="",0,IF(AND(F16>=Assumptions!$B$6,F16<=Assumptions!$B$5),1,0)) -> 0 | Q16: =P16*N16*Assumptions!$B$7 -> 0 | R16: =IF(AND(P16=1,J16>=Assumptions!$B$10),1,0) -> 0
A17: EMP2016 | B17: Operations | C17: Junior | D17: F | E17: 44186 | H17: 53000 | I17: 6 | J17: 2 | K17: =IF(F17="","Active","Left") -> Active | L17: =ROUND((IF(F17="",Assumptions!$B$5,F17)-E17)/365.25,1) -> 5.8 | M17: =IF(L17<1,"Under 1 yr",IF(L17<3,"1 to 3 yrs",IF(L17<5,"3 to 5 yrs","5+ yrs"))) -> 5+ yrs | N17: =H17*12 -> 636000 | O17: =IF(AND(E17<Assumptions!$B$6,OR(F17="",F17>=Assumptions!$B$6)),1,0) -> 1 | P17: =IF(F17="",0,IF(AND(F17>=Assumptions!$B$6,F17<=Assumptions!$B$5),1,0)) -> 0 | Q17: =P17*N17*Assumptions!$B$7 -> 0 | R17: =IF(AND(P17=1,J17>=Assumptions!$B$10),1,0) -> 0
A18: EMP2017 | B18: Customer Service | C18: Junior | D18: M | E18: 42250 | H18: 36000 | I18: 10 | J18: 4 | K18: =IF(F18="","Active","Left") -> Active | L18: =ROUND((IF(F18="",Assumptions!$B$5,F18)-E18)/365.25,1) -> 11.1 | M18: =IF(L18<1,"Under 1 yr",IF(L18<3,"1 to 3 yrs",IF(L18<5,"3 to 5 yrs","5+ yrs"))) -> 5+ yrs | N18: =H18*12 -> 432000 | O18: =IF(AND(E18<Assumptions!$B$6,OR(F18="",F18>=Assumptions!$B$6)),1,0) -> 1 | P18: =IF(F18="",0,IF(AND(F18>=Assumptions!$B$6,F18<=Assumptions!$B$5),1,0)) -> 0 | Q18: =P18*N18*Assumptions!$B$7 -> 0 | R18: =IF(AND(P18=1,J18>=Assumptions!$B$10),1,0) -> 0
A19: EMP2018 | B19: Sales | C19: Officer | D19: M | E19: 45715 | H19: 94000 | I19: 1 | J19: 2 | K19: =IF(F19="","Active","Left") -> Active | L19: =ROUND((IF(F19="",Assumptions!$B$5,F19)-E19)/365.25,1) -> 1.6 | M19: =IF(L19<1,"Under 1 yr",IF(L19<3,"1 to 3 yrs",IF(L19<5,"3 to 5 yrs","5+ yrs"))) -> 1 to 3 yrs | N19: =H19*12 -> 1128000 | O19: =IF(AND(E19<Assumptions!$B$6,OR(F19="",F19>=Assumptions!$B$6)),1,0) -> 1 | P19: =IF(F19="",0,IF(AND(F19>=Assumptions!$B$6,F19<=Assumptions!$B$5),1,0)) -> 0 | Q19: =P19*N19*Assumptions!$B$7 -> 0 | R19: =IF(AND(P19=1,J19>=Assumptions!$B$10),1,0) -> 0
A20: EMP2019 | B20: Operations | C20: Senior | D20: M | E20: 42079 | H20: 123000 | I20: 7 | J20: 3 | K20: =IF(F20="","Active","Left") -> Active | L20: =ROUND((IF(F20="",Assumptions!$B$5,F20)-E20)/365.25,1) -> 11.5 | M20: =IF(L20<1,"Under 1 yr",IF(L20<3,"1 to 3 yrs",IF(L20<5,"3 to 5 yrs","5+ yrs"))) -> 5+ yrs | N20: =H20*12 -> 1476000 | O20: =IF(AND(E20<Assumptions!$B$6,OR(F20="",F20>=Assumptions!$B$6)),1,0) -> 1 | P20: =IF(F20="",0,IF(AND(F20>=Assumptions!$B$6,F20<=Assumptions!$B$5),1,0)) -> 0 | Q20: =P20*N20*Assumptions!$B$7 -> 0 | R20: =IF(AND(P20=1,J20>=Assumptions!$B$10),1,0) -> 0
A21: EMP2020 | B21: Customer Service | C21: Junior | D21: M | E21: 44128 | H21: 60000 | I21: 12 | J21: 4 | K21: =IF(F21="","Active","Left") -> Active | L21: =ROUND((IF(F21="",Assumptions!$B$5,F21)-E21)/365.25,1) -> 5.9 | M21: =IF(L21<1,"Under 1 yr",IF(L21<3,"1 to 3 yrs",IF(L21<5,"3 to 5 yrs","5+ yrs"))) -> 5+ yrs | N21: =H21*12 -> 720000 | O21: =IF(AND(E21<Assumptions!$B$6,OR(F21="",F21>=Assumptions!$B$6)),1,0) -> 1 | P21: =IF(F21="",0,IF(AND(F21>=Assumptions!$B$6,F21<=Assumptions!$B$5),1,0)) -> 0 | Q21: =P21*N21*Assumptions!$B$7 -> 0 | R21: =IF(AND(P21=1,J21>=Assumptions!$B$10),1,0) -> 0
A22: EMP2021 | B22: Customer Service | C22: Manager | D22: F | E22: 43565 | H22: 292000 | I22: 8 | J22: 4 | K22: =IF(F22="","Active","Left") -> Active | L22: =ROUND((IF(F22="",Assumptions!$B$5,F22)-E22)/365.25,1) -> 7.5 | M22: =IF(L22<1,"Under 1 yr",IF(L22<3,"1 to 3 yrs",IF(L22<5,"3 to 5 yrs","5+ yrs"))) -> 5+ yrs | N22: =H22*12 -> 3504000 | O22: =IF(AND(E22<Assumptions!$B$6,OR(F22="",F22>=Assumptions!$B$6)),1,0) -> 1 | P22: =IF(F22="",0,IF(AND(F22>=Assumptions!$B$6,F22<=Assumptions!$B$5),1,0)) -> 0 | Q22: =P22*N22*Assumptions!$B$7 -> 0 | R22: =IF(AND(P22=1,J22>=Assumptions!$B$10),1,0) -> 0
A23: EMP2022 | B23: Sales | C23: Senior | D23: M | E23: 44776 | F23: 46195 | G23: Relocation | H23: 135000 | I23: 2 | J23: 4 | K23: =IF(F23="","Active","Left") -> Left | L23: =ROUND((IF(F23="",Assumptions!$B$5,F23)-E23)/365.25,1) -> 3.9 | M23: =IF(L23<1,"Under 1 yr",IF(L23<3,"1 to 3 yrs",IF(L23<5,"3 to 5 yrs","5+ yrs"))) -> 3 to 5 yrs | N23: =H23*12 -> 1620000 | O23: =IF(AND(E23<Assumptions!$B$6,OR(F23="",F23>=Assumptions!$B$6)),1,0) -> 1 | P23: =IF(F23="",0,IF(AND(F23>=Assumptions!$B$6,F23<=Assumptions!$B$5),1,0)) -> 1 | Q23: =P23*N23*Assumptions!$B$7 -> 810000 | R23: =IF(AND(P23=1,J23>=Assumptions!$B$10),1,0) -> 1
A24: EMP2023 | B24: IT | C24: Officer | D24: F | E24: 42183 | F24: 46189 | G24: Personal / family | H24: 100000 | I24: 5 | J24: 5 | K24: =IF(F24="","Active","Left") -> Left | L24: =ROUND((IF(F24="",Assumptions!$B$5,F24)-E24)/365.25,1) -> 11 | M24: =IF(L24<1,"Under 1 yr",IF(L24<3,"1 to 3 yrs",IF(L24<5,"3 to 5 yrs","5+ yrs"))) -> 5+ yrs | N24: =H24*12 -> 1200000 | O24: =IF(AND(E24<Assumptions!$B$6,OR(F24="",F24>=Assumptions!$B$6)),1,0) -> 1 | P24: =IF(F24="",0,IF(AND(F24>=Assumptions!$B$6,F24<=Assumptions!$B$5),1,0)) -> 1 | Q24: =P24*N24*Assumptions!$B$7 -> 600000 | R24: =IF(AND(P24=1,J24>=Assumptions!$B$10),1,0) -> 1
A25: EMP2024 | B25: Operations | C25: Junior | D25: M | E25: 44565 | H25: 54000 | I25: 3 | J25: 3 | K25: =IF(F25="","Active","Left") -> Active | L25: =ROUND((IF(F25="",Assumptions!$B$5,F25)-E25)/365.25,1) -> 4.7 | M25: =IF(L25<1,"Under 1 yr",IF(L25<3,"1 to 3 yrs",IF(L25<5,"3 to 5 yrs","5+ yrs"))) -> 3 to 5 yrs | N25: =H25*12 -> 648000 | O25: =IF(AND(E25<Assumptions!$B$6,OR(F25="",F25>=Assumptions!$B$6)),1,0) -> 1 | P25: =IF(F25="",0,IF(AND(F25>=Assumptions!$B$6,F25<=Assumptions!$B$5),1,0)) -> 0 | Q25: =P25*N25*Assumptions!$B$7 -> 0 | R25: =IF(AND(P25=1,J25>=Assumptions!$B$10),1,0) -> 0
A26: EMP2025 | B26: HR | C26: Senior | D26: F | E26: 42433 | H26: 151000 | I26: 4 | J26: 2 | K26: =IF(F26="","Active","Left") -> Active | L26: =ROUND((IF(F26="",Assumptions!$B$5,F26)-E26)/365.25,1) -> 10.6 | M26: =IF(L26<1,"Under 1 yr",IF(L26<3,"1 to 3 yrs",IF(L26<5,"3 to 5 yrs","5+ yrs"))) -> 5+ yrs | N26: =H26*12 -> 1812000 | O26: =IF(AND(E26<Assumptions!$B$6,OR(F26="",F26>=Assumptions!$B$6)),1,0) -> 1 | P26: =IF(F26="",0,IF(AND(F26>=Assumptions!$B$6,F26<=Assumptions!$B$5),1,0)) -> 0 | Q26: =P26*N26*Assumptions!$B$7 -> 0 | R26: =IF(AND(P26=1,J26>=Assumptions!$B$10),1,0) -> 0
A27: EMP2026 | B27: Customer Service | C27: Junior | D27: M | E27: 42200 | H27: 49000 | I27: 7 | J27: 5 | K27: =IF(F27="","Active","Left") -> Active | L27: =ROUND((IF(F27="",Assumptions!$B$5,F27)-E27)/365.25,1) -> 11.2 | M27: =IF(L27<1,"Under 1 yr",IF(L27<3,"1 to 3 yrs",IF(L27<5,"3 to 5 yrs","5+ yrs"))) -> 5+ yrs | N27: =H27*12 -> 588000 | O27: =IF(AND(E27<Assumptions!$B$6,OR(F27="",F27>=Assumptions!$B$6)),1,0) -> 1 | P27: =IF(F27="",0,IF(AND(F27>=Assumptions!$B$6,F27<=Assumptions!$B$5),1,0)) -> 0 | Q27: =P27*N27*Assumptions!$B$7 -> 0 | R27: =IF(AND(P27=1,J27>=Assumptions!$B$10),1,0) -> 0
A28: EMP2027 | B28: Sales | C28: Junior | D28: M | E28: 45233 | H28: 44000 | I28: 5 | J28: 5 | K28: =IF(F28="","Active","Left") -> Active | L28: =ROUND((IF(F28="",Assumptions!$B$5,F28)-E28)/365.25,1) -> 2.9 | M28: =IF(L28<1,"Under 1 yr",IF(L28<3,"1 to 3 yrs",IF(L28<5,"3 to 5 yrs","5+ yrs"))) -> 1 to 3 yrs | N28: =H28*12 -> 528000 | O28: =IF(AND(E28<Assumptions!$B$6,OR(F28="",F28>=Assumptions!$B$6)),1,0) -> 1 | P28: =IF(F28="",0,IF(AND(F28>=Assumptions!$B$6,F28<=Assumptions!$B$5),1,0)) -> 0 | Q28: =P28*N28*Assumptions!$B$7 -> 0 | R28: =IF(AND(P28=1,J28>=Assumptions!$B$10),1,0) -> 0
A29: EMP2028 | B29: Finance | C29: Junior | D29: F | E29: 43787 | F29: 46052 | G29: Poor management | H29: 52000 | I29: 7 | J29: 3 | K29: =IF(F29="","Active","Left") -> Left | L29: =ROUND((IF(F29="",Assumptions!$B$5,F29)-E29)/365.25,1) -> 6.2 | M29: =IF(L29<1,"Under 1 yr",IF(L29<3,"1 to 3 yrs",IF(L29<5,"3 to 5 yrs","5+ yrs"))) -> 5+ yrs | N29: =H29*12 -> 624000 | O29: =IF(AND(E29<Assumptions!$B$6,OR(F29="",F29>=Assumptions!$B$6)),1,0) -> 1 | P29: =IF(F29="",0,IF(AND(F29>=Assumptions!$B$6,F29<=Assumptions!$B$5),1,0)) -> 1 | Q29: =P29*N29*Assumptions!$B$7 -> 312000 | R29: =IF(AND(P29=1,J29>=Assumptions!$B$10),1,0) -> 0
A30: EMP2029 | B30: Operations | C30: Junior | D30: M | E30: 43256 | F30: 46176 | G30: Career growth | H30: 40000 | I30: 3 | J30: 3 | K30: =IF(F30="","Active","Left") -> Left | L30: =ROUND((IF(F30="",Assumptions!$B$5,F30)-E30)/365.25,1) -> 8 | M30: =IF(L30<1,"Under 1 yr",IF(L30<3,"1 to 3 yrs",IF(L30<5,"3 to 5 yrs","5+ yrs"))) -> 5+ yrs | N30: =H30*12 -> 480000 | O30: =IF(AND(E30<Assumptions!$B$6,OR(F30="",F30>=Assumptions!$B$6)),1,0) -> 1 | P30: =IF(F30="",0,IF(AND(F30>=Assumptions!$B$6,F30<=Assumptions!$B$5),1,0)) -> 1 | Q30: =P30*N30*Assumptions!$B$7 -> 240000 | R30: =IF(AND(P30=1,J30>=Assumptions!$B$10),1,0) -> 0
A31: EMP2030 | B31: Sales | C31: Officer | D31: M | E31: 45764 | H31: 85000 | I31: 4 | J31: 4 | K31: =IF(F31="","Active","Left") -> Active | L31: =ROUND((IF(F31="",Assumptions!$B$5,F31)-E31)/365.25,1) -> 1.5 | M31: =IF(L31<1,"Under 1 yr",IF(L31<3,"1 to 3 yrs",IF(L31<5,"3 to 5 yrs","5+ yrs"))) -> 1 to 3 yrs | N31: =H31*12 -> 1020000 | O31: =IF(AND(E31<Assumptions!$B$6,OR(F31="",F31>=Assumptions!$B$6)),1,0) -> 1 | P31: =IF(F31="",0,IF(AND(F31>=Assumptions!$B$6,F31<=Assumptions!$B$5),1,0)) -> 0 | Q31: =P31*N31*Assumptions!$B$7 -> 0 | R31: =IF(AND(P31=1,J31>=Assumptions!$B$10),1,0) -> 0
A32: EMP2031 | B32: HR | C32: Junior | D32: F | E32: 44347 | H32: 38000 | I32: 6 | J32: 3 | K32: =IF(F32="","Active","Left") -> Active | L32: =ROUND((IF(F32="",Assumptions!$B$5,F32)-E32)/365.25,1) -> 5.3 | M32: =IF(L32<1,"Under 1 yr",IF(L32<3,"1 to 3 yrs",IF(L32<5,"3 to 5 yrs","5+ yrs"))) -> 5+ yrs | N32: =H32*12 -> 456000 | O32: =IF(AND(E32<Assumptions!$B$6,OR(F32="",F32>=Assumptions!$B$6)),1,0) -> 1 | P32: =IF(F32="",0,IF(AND(F32>=Assumptions!$B$6,F32<=Assumptions!$B$5),1,0)) -> 0 | Q32: =P32*N32*Assumptions!$B$7 -> 0 | R32: =IF(AND(P32=1,J32>=Assumptions!$B$10),1,0) -> 0
A33: EMP2032 | B33: Finance | C33: Officer | D33: F | E33: 43030 | F33: 46012 | G33: Personal / family | H33: 79000 | I33: 7 | J33: 3 | K33: =IF(F33="","Active","Left") -> Left | L33: =ROUND((IF(F33="",Assumptions!$B$5,F33)-E33)/365.25,1) -> 8.2 | M33: =IF(L33<1,"Under 1 yr",IF(L33<3,"1 to 3 yrs",IF(L33<5,"3 to 5 yrs","5+ yrs"))) -> 5+ yrs | N33: =H33*12 -> 948000 | O33: =IF(AND(E33<Assumptions!$B$6,OR(F33="",F33>=Assumptions!$B$6)),1,0) -> 1 | P33: =IF(F33="",0,IF(AND(F33>=Assumptions!$B$6,F33<=Assumptions!$B$5),1,0)) -> 1 | Q33: =P33*N33*Assumptions!$B$7 -> 474000 | R33: =IF(AND(P33=1,J33>=Assumptions!$B$10),1,0) -> 0
A34: EMP2033 | B34: Operations | C34: Senior | D34: M | E34: 45266 | H34: 161000 | I34: 3 | J34: 3 | K34: =IF(F34="","Active","Left") -> Active | L34: =ROUND((IF(F34="",Assumptions!$B$5,F34)-E34)/365.25,1) -> 2.8 | M34: =IF(L34<1,"Under 1 yr",IF(L34<3,"1 to 3 yrs",IF(L34<5,"3 to 5 yrs","5+ yrs"))) -> 1 to 3 yrs | N34: =H34*12 -> 1932000 | O34: =IF(AND(E34<Assumptions!$B$6,OR(F34="",F34>=Assumptions!$B$6)),1,0) -> 1 | P34: =IF(F34="",0,IF(AND(F34>=Assumptions!$B$6,F34<=Assumptions!$B$5),1,0)) -> 0 | Q34: =P34*N34*Assumptions!$B$7 -> 0 | R34: =IF(AND(P34=1,J34>=Assumptions!$B$10),1,0) -> 0
A35: EMP2034 | B35: Customer Service | C35: Senior | D35: F | E35: 43851 | H35: 147000 | I35: 5 | J35: 4 | K35: =IF(F35="","Active","Left") -> Active | L35: =ROUND((IF(F35="",Assumptions!$B$5,F35)-E35)/365.25,1) -> 6.7 | M35: =IF(L35<1,"Under 1 yr",IF(L35<3,"1 to 3 yrs",IF(L35<5,"3 to 5 yrs","5+ yrs"))) -> 5+ yrs | N35: =H35*12 -> 1764000 | O35: =IF(AND(E35<Assumptions!$B$6,OR(F35="",F35>=Assumptions!$B$6)),1,0) -> 1 | P35: =IF(F35="",0,IF(AND(F35>=Assumptions!$B$6,F35<=Assumptions!$B$5),1,0)) -> 0 | Q35: =P35*N35*Assumptions!$B$7 -> 0 | R35: =IF(AND(P35=1,J35>=Assumptions!$B$10),1,0) -> 0
A36: EMP2035 | B36: Operations | C36: Officer | D36: M | E36: 44909 | H36: 67000 | I36: 3 | J36: 3 | K36: =IF(F36="","Active","Left") -> Active | L36: =ROUND((IF(F36="",Assumptions!$B$5,F36)-E36)/365.25,1) -> 3.8 | M36: =IF(L36<1,"Under 1 yr",IF(L36<3,"1 to 3 yrs",IF(L36<5,"3 to 5 yrs","5+ yrs"))) -> 3 to 5 yrs | N36: =H36*12 -> 804000 | O36: =IF(AND(E36<Assumptions!$B$6,OR(F36="",F36>=Assumptions!$B$6)),1,0) -> 1 | P36: =IF(F36="",0,IF(AND(F36>=Assumptions!$B$6,F36<=Assumptions!$B$5),1,0)) -> 0 | Q36: =P36*N36*Assumptions!$B$7 -> 0 | R36: =IF(AND(P36=1,J36>=Assumptions!$B$10),1,0) -> 0
A37: EMP2036 | B37: Customer Service | C37: Junior | D37: F | E37: 46133 | H37: 39000 | I37: 6 | J37: 3 | K37: =IF(F37="","Active","Left") -> Active | L37: =ROUND((IF(F37="",Assumptions!$B$5,F37)-E37)/365.25,1) -> 0.4 | M37: =IF(L37<1,"Under 1 yr",IF(L37<3,"1 to 3 yrs",IF(L37<5,"3 to 5 yrs","5+ yrs"))) -> Under 1 yr | N37: =H37*12 -> 468000 | O37: =IF(AND(E37<Assumptions!$B$6,OR(F37="",F37>=Assumptions!$B$6)),1,0) -> 0 | P37: =IF(F37="",0,IF(AND(F37>=Assumptions!$B$6,F37<=Assumptions!$B$5),1,0)) -> 0 | Q37: =P37*N37*Assumptions!$B$7 -> 0 | R37: =IF(AND(P37=1,J37>=Assumptions!$B$10),1,0) -> 0
A38: EMP2037 | B38: Sales | C38: Officer | D38: F | E38: 44142 | F38: 46014 | G38: Career growth | H38: 70000 | I38: 3 | J38: 4 | K38: =IF(F38="","Active","Left") -> Left | L38: =ROUND((IF(F38="",Assumptions!$B$5,F38)-E38)/365.25,1) -> 5.1 | M38: =IF(L38<1,"Under 1 yr",IF(L38<3,"1 to 3 yrs",IF(L38<5,"3 to 5 yrs","5+ yrs"))) -> 5+ yrs | N38: =H38*12 -> 840000 | O38: =IF(AND(E38<Assumptions!$B$6,OR(F38="",F38>=Assumptions!$B$6)),1,0) -> 1 | P38: =IF(F38="",0,IF(AND(F38>=Assumptions!$B$6,F38<=Assumptions!$B$5),1,0)) -> 1 | Q38: =P38*N38*Assumptions!$B$7 -> 420000 | R38: =IF(AND(P38=1,J38>=Assumptions!$B$10),1,0) -> 1
A39: EMP2038 | B39: Operations | C39: Junior | D39: M | E39: 43397 | H39: 51000 | I39: 5 | J39: 4 | K39: =IF(F39="","Active","Left") -> Active | L39: =ROUND((IF(F39="",Assumptions!$B$5,F39)-E39)/365.25,1) -> 7.9 | M39: =IF(L39<1,"Under 1 yr",IF(L39<3,"1 to 3 yrs",IF(L39<5,"3 to 5 yrs","5+ yrs"))) -> 5+ yrs | N39: =H39*12 -> 612000 | O39: =IF(AND(E39<Assumptions!$B$6,OR(F39="",F39>=Assumptions!$B$6)),1,0) -> 1 | P39: =IF(F39="",0,IF(AND(F39>=Assumptions!$B$6,F39<=Assumptions!$B$5),1,0)) -> 0 | Q39: =P39*N39*Assumptions!$B$7 -> 0 | R39: =IF(AND(P39=1,J39>=Assumptions!$B$10),1,0) -> 0
A40: EMP2039 | B40: Finance | C40: Junior | D40: F | E40: 44643 | H40: 55000 | I40: 6 | J40: 1 | K40: =IF(F40="","Active","Left") -> Active | L40: =ROUND((IF(F40="",Assumptions!$B$5,F40)-E40)/365.25,1) -> 4.5 | M40: =IF(L40<1,"Under 1 yr",IF(L40<3,"1 to 3 yrs",IF(L40<5,"3 to 5 yrs","5+ yrs"))) -> 3 to 5 yrs | N40: =H40*12 -> 660000 | O40: =IF(AND(E40<Assumptions!$B$6,OR(F40="",F40>=Assumptions!$B$6)),1,0) -> 1 | P40: =IF(F40="",0,IF(AND(F40>=Assumptions!$B$6,F40<=Assumptions!$B$5),1,0)) -> 0 | Q40: =P40*N40*Assumptions!$B$7 -> 0 | R40: =IF(AND(P40=1,J40>=Assumptions!$B$10),1,0) -> 0
A41: EMP2040 | B41: Finance | C41: Manager | D41: F | E41: 45386 | H41: 235000 | I41: 5 | J41: 3 | K41: =IF(F41="","Active","Left") -> Active | L41: =ROUND((IF(F41="",Assumptions!$B$5,F41)-E41)/365.25,1) -> 2.5 | M41: =IF(L41<1,"Under 1 yr",IF(L41<3,"1 to 3 yrs",IF(L41<5,"3 to 5 yrs","5+ yrs"))) -> 1 to 3 yrs | N41: =H41*12 -> 2820000 | O41: =IF(AND(E41<Assumptions!$B$6,OR(F41="",F41>=Assumptions!$B$6)),1,0) -> 1 | P41: =IF(F41="",0,IF(AND(F41>=Assumptions!$B$6,F41<=Assumptions!$B$5),1,0)) -> 0 | Q41: =P41*N41*Assumptions!$B$7 -> 0 | R41: =IF(AND(P41=1,J41>=Assumptions!$B$10),1,0) -> 0
A42: EMP2041 | B42: Customer Service | C42: Officer | D42: M | E42: 42350 | H42: 77000 | I42: 11 | J42: 3 | K42: =IF(F42="","Active","Left") -> Active | L42: =ROUND((IF(F42="",Assumptions!$B$5,F42)-E42)/365.25,1) -> 10.8 | M42: =IF(L42<1,"Under 1 yr",IF(L42<3,"1 to 3 yrs",IF(L42<5,"3 to 5 yrs","5+ yrs"))) -> 5+ yrs | N42: =H42*12 -> 924000 | O42: =IF(AND(E42<Assumptions!$B$6,OR(F42="",F42>=Assumptions!$B$6)),1,0) -> 1 | P42: =IF(F42="",0,IF(AND(F42>=Assumptions!$B$6,F42<=Assumptions!$B$5),1,0)) -> 0 | Q42: =P42*N42*Assumptions!$B$7 -> 0 | R42: =IF(AND(P42=1,J42>=Assumptions!$B$10),1,0) -> 0
A43: EMP2042 | B43: Customer Service | C43: Officer | D43: M | E43: 42602 | F43: 45936 | G43: Career growth | H43: 84000 | I43: 13 | J43: 2 | K43: =IF(F43="","Active","Left") -> Left | L43: =ROUND((IF(F43="",Assumptions!$B$5,F43)-E43)/365.25,1) -> 9.1 | M43: =IF(L43<1,"Under 1 yr",IF(L43<3,"1 to 3 yrs",IF(L43<5,"3 to 5 yrs","5+ yrs"))) -> 5+ yrs | N43: =H43*12 -> 1008000 | O43: =IF(AND(E43<Assumptions!$B$6,OR(F43="",F43>=Assumptions!$B$6)),1,0) -> 1 | P43: =IF(F43="",0,IF(AND(F43>=Assumptions!$B$6,F43<=Assumptions!$B$5),1,0)) -> 1 | Q43: =P43*N43*Assumptions!$B$7 -> 504000 | R43: =IF(AND(P43=1,J43>=Assumptions!$B$10),1,0) -> 0
A44: EMP2043 | B44: IT | C44: Senior | D44: F | E44: 45190 | H44: 131000 | I44: 15 | J44: 1 | K44: =IF(F44="","Active","Left") -> Active | L44: =ROUND((IF(F44="",Assumptions!$B$5,F44)-E44)/365.25,1) -> 3 | M44: =IF(L44<1,"Under 1 yr",IF(L44<3,"1 to 3 yrs",IF(L44<5,"3 to 5 yrs","5+ yrs"))) -> 3 to 5 yrs | N44: =H44*12 -> 1572000 | O44: =IF(AND(E44<Assumptions!$B$6,OR(F44="",F44>=Assumptions!$B$6)),1,0) -> 1 | P44: =IF(F44="",0,IF(AND(F44>=Assumptions!$B$6,F44<=Assumptions!$B$5),1,0)) -> 0 | Q44: =P44*N44*Assumptions!$B$7 -> 0 | R44: =IF(AND(P44=1,J44>=Assumptions!$B$10),1,0) -> 0
A45: EMP2044 | B45: Customer Service | C45: Junior | D45: F | E45: 43494 | H45: 35000 | I45: 3 | J45: 2 | K45: =IF(F45="","Active","Left") -> Active | L45: =ROUND((IF(F45="",Assumptions!$B$5,F45)-E45)/365.25,1) -> 7.7 | M45: =IF(L45<1,"Under 1 yr",IF(L45<3,"1 to 3 yrs",IF(L45<5,"3 to 5 yrs","5+ yrs"))) -> 5+ yrs | N45: =H45*12 -> 420000 | O45: =IF(AND(E45<Assumptions!$B$6,OR(F45="",F45>=Assumptions!$B$6)),1,0) -> 1 | P45: =IF(F45="",0,IF(AND(F45>=Assumptions!$B$6,F45<=Assumptions!$B$5),1,0)) -> 0 | Q45: =P45*N45*Assumptions!$B$7 -> 0 | R45: =IF(AND(P45=1,J45>=Assumptions!$B$10),1,0) -> 0
A46: EMP2045 | B46: Operations | C46: Officer | D46: M | E46: 45998 | H46: 102000 | I46: 3 | J46: 2 | K46: =IF(F46="","Active","Left") -> Active | L46: =ROUND((IF(F46="",Assumptions!$B$5,F46)-E46)/365.25,1) -> 0.8 | M46: =IF(L46<1,"Under 1 yr",IF(L46<3,"1 to 3 yrs",IF(L46<5,"3 to 5 yrs","5+ yrs"))) -> Under 1 yr | N46: =H46*12 -> 1224000 | O46: =IF(AND(E46<Assumptions!$B$6,OR(F46="",F46>=Assumptions!$B$6)),1,0) -> 0 | P46: =IF(F46="",0,IF(AND(F46>=Assumptions!$B$6,F46<=Assumptions!$B$5),1,0)) -> 0 | Q46: =P46*N46*Assumptions!$B$7 -> 0 | R46: =IF(AND(P46=1,J46>=Assumptions!$B$10),1,0) -> 0
A47: EMP2046 | B47: Finance | C47: Junior | D47: M | E47: 43550 | H47: 60000 | I47: 6 | J47: 4 | K47: =IF(F47="","Active","Left") -> Active | L47: =ROUND((IF(F47="",Assumptions!$B$5,F47)-E47)/365.25,1) -> 7.5 | M47: =IF(L47<1,"Under 1 yr",IF(L47<3,"1 to 3 yrs",IF(L47<5,"3 to 5 yrs","5+ yrs"))) -> 5+ yrs | N47: =H47*12 -> 720000 | O47: =IF(AND(E47<Assumptions!$B$6,OR(F47="",F47>=Assumptions!$B$6)),1,0) -> 1 | P47: =IF(F47="",0,IF(AND(F47>=Assumptions!$B$6,F47<=Assumptions!$B$5),1,0)) -> 0 | Q47: =P47*N47*Assumptions!$B$7 -> 0 | R47: =IF(AND(P47=1,J47>=Assumptions!$B$10),1,0) -> 0
A48: EMP2047 | B48: Operations | C48: Senior | D48: M | E48: 45772 | H48: 171000 | I48: 5 | J48: 1 | K48: =IF(F48="","Active","Left") -> Active | L48: =ROUND((IF(F48="",Assumptions!$B$5,F48)-E48)/365.25,1) -> 1.4 | M48: =IF(L48<1,"Under 1 yr",IF(L48<3,"1 to 3 yrs",IF(L48<5,"3 to 5 yrs","5+ yrs"))) -> 1 to 3 yrs | N48: =H48*12 -> 2052000 | O48: =IF(AND(E48<Assumptions!$B$6,OR(F48="",F48>=Assumptions!$B$6)),1,0) -> 1 | P48: =IF(F48="",0,IF(AND(F48>=Assumptions!$B$6,F48<=Assumptions!$B$5),1,0)) -> 0 | Q48: =P48*N48*Assumptions!$B$7 -> 0 | R48: =IF(AND(P48=1,J48>=Assumptions!$B$10),1,0) -> 0
A49: EMP2048 | B49: Sales | C49: Officer | D49: F | E49: 44871 | F49: 46256 | G49: Better pay elsewhere | H49: 86000 | I49: 6 | J49: 2 | K49: =IF(F49="","Active","Left") -> Left | L49: =ROUND((IF(F49="",Assumptions!$B$5,F49)-E49)/365.25,1) -> 3.8 | M49: =IF(L49<1,"Under 1 yr",IF(L49<3,"1 to 3 yrs",IF(L49<5,"3 to 5 yrs","5+ yrs"))) -> 3 to 5 yrs | N49: =H49*12 -> 1032000 | O49: =IF(AND(E49<Assumptions!$B$6,OR(F49="",F49>=Assumptions!$B$6)),1,0) -> 1 | P49: =IF(F49="",0,IF(AND(F49>=Assumptions!$B$6,F49<=Assumptions!$B$5),1,0)) -> 1 | Q49: =P49*N49*Assumptions!$B$7 -> 516000 | R49: =IF(AND(P49=1,J49>=Assumptions!$B$10),1,0) -> 0
A50: EMP2049 | B50: IT | C50: Junior | D50: M | E50: 45948 | H50: 46000 | I50: 6 | J50: 5 | K50: =IF(F50="","Active","Left") -> Active | L50: =ROUND((IF(F50="",Assumptions!$B$5,F50)-E50)/365.25,1) -> 1 | M50: =IF(L50<1,"Under 1 yr",IF(L50<3,"1 to 3 yrs",IF(L50<5,"3 to 5 yrs","5+ yrs"))) -> 1 to 3 yrs | N50: =H50*12 -> 552000 | O50: =IF(AND(E50<Assumptions!$B$6,OR(F50="",F50>=Assumptions!$B$6)),1,0) -> 0 | P50: =IF(F50="",0,IF(AND(F50>=Assumptions!$B$6,F50<=Assumptions!$B$5),1,0)) -> 0 | Q50: =P50*N50*Assumptions!$B$7 -> 0 | R50: =IF(AND(P50=1,J50>=Assumptions!$B$10),1,0) -> 0
A51: EMP2050 | B51: Customer Service | C51: Officer | D51: M | E51: 44858 | H51: 64000 | I51: 9 | J51: 4 | K51: =IF(F51="","Active","Left") -> Active | L51: =ROUND((IF(F51="",Assumptions!$B$5,F51)-E51)/365.25,1) -> 3.9 | M51: =IF(L51<1,"Under 1 yr",IF(L51<3,"1 to 3 yrs",IF(L51<5,"3 to 5 yrs","5+ yrs"))) -> 3 to 5 yrs | N51: =H51*12 -> 768000 | O51: =IF(AND(E51<Assumptions!$B$6,OR(F51="",F51>=Assumptions!$B$6)),1,0) -> 1 | P51: =IF(F51="",0,IF(AND(F51>=Assumptions!$B$6,F51<=Assumptions!$B$5),1,0)) -> 0 | Q51: =P51*N51*Assumptions!$B$7 -> 0 | R51: =IF(AND(P51=1,J51>=Assumptions!$B$10),1,0) -> 0
A52: EMP2051 | B52: IT | C52: Junior | D52: F | E52: 43738 | F52: 46093 | G52: Better pay elsewhere | H52: 37000 | I52: 6 | J52: 3 | K52: =IF(F52="","Active","Left") -> Left | L52: =ROUND((IF(F52="",Assumptions!$B$5,F52)-E52)/365.25,1) -> 6.4 | M52: =IF(L52<1,"Under 1 yr",IF(L52<3,"1 to 3 yrs",IF(L52<5,"3 to 5 yrs","5+ yrs"))) -> 5+ yrs | N52: =H52*12 -> 444000 | O52: =IF(AND(E52<Assumptions!$B$6,OR(F52="",F52>=Assumptions!$B$6)),1,0) -> 1 | P52: =IF(F52="",0,IF(AND(F52>=Assumptions!$B$6,F52<=Assumptions!$B$5),1,0)) -> 1 | Q52: =P52*N52*Assumptions!$B$7 -> 222000 | R52: =IF(AND(P52=1,J52>=Assumptions!$B$10),1,0) -> 0
A53: EMP2052 | B53: Customer Service | C53: Junior | D53: F | E53: 42986 | H53: 35000 | I53: 7 | J53: 4 | K53: =IF(F53="","Active","Left") -> Active | L53: =ROUND((IF(F53="",Assumptions!$B$5,F53)-E53)/365.25,1) -> 9.1 | M53: =IF(L53<1,"Under 1 yr",IF(L53<3,"1 to 3 yrs",IF(L53<5,"3 to 5 yrs","5+ yrs"))) -> 5+ yrs | N53: =H53*12 -> 420000 | O53: =IF(AND(E53<Assumptions!$B$6,OR(F53="",F53>=Assumptions!$B$6)),1,0) -> 1 | P53: =IF(F53="",0,IF(AND(F53>=Assumptions!$B$6,F53<=Assumptions!$B$5),1,0)) -> 0 | Q53: =P53*N53*Assumptions!$B$7 -> 0 | R53: =IF(AND(P53=1,J53>=Assumptions!$B$10),1,0) -> 0
A54: EMP2053 | B54: Customer Service | C54: Officer | D54: M | E54: 45805 | H54: 108000 | I54: 5 | J54: 3 | K54: =IF(F54="","Active","Left") -> Active | L54: =ROUND((IF(F54="",Assumptions!$B$5,F54)-E54)/365.25,1) -> 1.3 | M54: =IF(L54<1,"Under 1 yr",IF(L54<3,"1 to 3 yrs",IF(L54<5,"3 to 5 yrs","5+ yrs"))) -> 1 to 3 yrs | N54: =H54*12 -> 1296000 | O54: =IF(AND(E54<Assumptions!$B$6,OR(F54="",F54>=Assumptions!$B$6)),1,0) -> 1 | P54: =IF(F54="",0,IF(AND(F54>=Assumptions!$B$6,F54<=Assumptions!$B$5),1,0)) -> 0 | Q54: =P54*N54*Assumptions!$B$7 -> 0 | R54: =IF(AND(P54=1,J54>=Assumptions!$B$10),1,0) -> 0
A55: EMP2054 | B55: Operations | C55: Junior | D55: M | E55: 45628 | H55: 51000 | I55: 4 | J55: 3 | K55: =IF(F55="","Active","Left") -> Active | L55: =ROUND((IF(F55="",Assumptions!$B$5,F55)-E55)/365.25,1) -> 1.8 | M55: =IF(L55<1,"Under 1 yr",IF(L55<3,"1 to 3 yrs",IF(L55<5,"3 to 5 yrs","5+ yrs"))) -> 1 to 3 yrs | N55: =H55*12 -> 612000 | O55: =IF(AND(E55<Assumptions!$B$6,OR(F55="",F55>=Assumptions!$B$6)),1,0) -> 1 | P55: =IF(F55="",0,IF(AND(F55>=Assumptions!$B$6,F55<=Assumptions!$B$5),1,0)) -> 0 | Q55: =P55*N55*Assumptions!$B$7 -> 0 | R55: =IF(AND(P55=1,J55>=Assumptions!$B$10),1,0) -> 0
A56: EMP2055 | B56: Sales | C56: Officer | D56: M | E56: 42377 | H56: 61000 | I56: 12 | J56: 3 | K56: =IF(F56="","Active","Left") -> Active | L56: =ROUND((IF(F56="",Assumptions!$B$5,F56)-E56)/365.25,1) -> 10.7 | M56: =IF(L56<1,"Under 1 yr",IF(L56<3,"1 to 3 yrs",IF(L56<5,"3 to 5 yrs","5+ yrs"))) -> 5+ yrs | N56: =H56*12 -> 732000 | O56: =IF(AND(E56<Assumptions!$B$6,OR(F56="",F56>=Assumptions!$B$6)),1,0) -> 1 | P56: =IF(F56="",0,IF(AND(F56>=Assumptions!$B$6,F56<=Assumptions!$B$5),1,0)) -> 0 | Q56: =P56*N56*Assumptions!$B$7 -> 0 | R56: =IF(AND(P56=1,J56>=Assumptions!$B$10),1,0) -> 0
A57: EMP2056 | B57: Operations | C57: Officer | D57: M | E57: 46113 | F57: 46187 | G57: Contract ended | H57: 98000 | I57: 6 | J57: 3 | K57: =IF(F57="","Active","Left") -> Left | L57: =ROUND((IF(F57="",Assumptions!$B$5,F57)-E57)/365.25,1) -> 0.2 | M57: =IF(L57<1,"Under 1 yr",IF(L57<3,"1 to 3 yrs",IF(L57<5,"3 to 5 yrs","5+ yrs"))) -> Under 1 yr | N57: =H57*12 -> 1176000 | O57: =IF(AND(E57<Assumptions!$B$6,OR(F57="",F57>=Assumptions!$B$6)),1,0) -> 0 | P57: =IF(F57="",0,IF(AND(F57>=Assumptions!$B$6,F57<=Assumptions!$B$5),1,0)) -> 1 | Q57: =P57*N57*Assumptions!$B$7 -> 588000 | R57: =IF(AND(P57=1,J57>=Assumptions!$B$10),1,0) -> 0
A58: EMP2057 | B58: Operations | C58: Senior | D58: M | E58: 42777 | H58: 159000 | I58: 3 | J58: 4 | K58: =IF(F58="","Active","Left") -> Active | L58: =ROUND((IF(F58="",Assumptions!$B$5,F58)-E58)/365.25,1) -> 9.6 | M58: =IF(L58<1,"Under 1 yr",IF(L58<3,"1 to 3 yrs",IF(L58<5,"3 to 5 yrs","5+ yrs"))) -> 5+ yrs | N58: =H58*12 -> 1908000 | O58: =IF(AND(E58<Assumptions!$B$6,OR(F58="",F58>=Assumptions!$B$6)),1,0) -> 1 | P58: =IF(F58="",0,IF(AND(F58>=Assumptions!$B$6,F58<=Assumptions!$B$5),1,0)) -> 0 | Q58: =P58*N58*Assumptions!$B$7 -> 0 | R58: =IF(AND(P58=1,J58>=Assumptions!$B$10),1,0) -> 0
A59: EMP2058 | B59: Customer Service | C59: Junior | D59: M | E59: 45006 | H59: 58000 | I59: 10 | J59: 5 | K59: =IF(F59="","Active","Left") -> Active | L59: =ROUND((IF(F59="",Assumptions!$B$5,F59)-E59)/365.25,1) -> 3.5 | M59: =IF(L59<1,"Under 1 yr",IF(L59<3,"1 to 3 yrs",IF(L59<5,"3 to 5 yrs","5+ yrs"))) -> 3 to 5 yrs | N59: =H59*12 -> 696000 | O59: =IF(AND(E59<Assumptions!$B$6,OR(F59="",F59>=Assumptions!$B$6)),1,0) -> 1 | P59: =IF(F59="",0,IF(AND(F59>=Assumptions!$B$6,F59<=Assumptions!$B$5),1,0)) -> 0 | Q59: =P59*N59*Assumptions!$B$7 -> 0 | R59: =IF(AND(P59=1,J59>=Assumptions!$B$10),1,0) -> 0
A60: EMP2059 | B60: Customer Service | C60: Officer | D60: F | E60: 43415 | H60: 91000 | I60: 9 | J60: 3 | K60: =IF(F60="","Active","Left") -> Active | L60: =ROUND((IF(F60="",Assumptions!$B$5,F60)-E60)/365.25,1) -> 7.9 | M60: =IF(L60<1,"Under 1 yr",IF(L60<3,"1 to 3 yrs",IF(L60<5,"3 to 5 yrs","5+ yrs"))) -> 5+ yrs | N60: =H60*12 -> 1092000 | O60: =IF(AND(E60<Assumptions!$B$6,OR(F60="",F60>=Assumptions!$B$6)),1,0) -> 1 | P60: =IF(F60="",0,IF(AND(F60>=Assumptions!$B$6,F60<=Assumptions!$B$5),1,0)) -> 0 | Q60: =P60*N60*Assumptions!$B$7 -> 0 | R60: =IF(AND(P60=1,J60>=Assumptions!$B$10),1,0) -> 0
A61: EMP2060 | B61: Finance | C61: Junior | D61: M | E61: 45074 | H61: 49000 | I61: 6 | J61: 2 | K61: =IF(F61="","Active","Left") -> Active | L61: =ROUND((IF(F61="",Assumptions!$B$5,F61)-E61)/365.25,1) -> 3.3 | M61: =IF(L61<1,"Under 1 yr",IF(L61<3,"1 to 3 yrs",IF(L61<5,"3 to 5 yrs","5+ yrs"))) -> 3 to 5 yrs | N61: =H61*12 -> 588000 | O61: =IF(AND(E61<Assumptions!$B$6,OR(F61="",F61>=Assumptions!$B$6)),1,0) -> 1 | P61: =IF(F61="",0,IF(AND(F61>=Assumptions!$B$6,F61<=Assumptions!$B$5),1,0)) -> 0 | Q61: =P61*N61*Assumptions!$B$7 -> 0 | R61: =IF(AND(P61=1,J61>=Assumptions!$B$10),1,0) -> 0
A62: EMP2061 | B62: Operations | C62: Officer | D62: M | E62: 46050 | H62: 69000 | I62: 6 | J62: 3 | K62: =IF(F62="","Active","Left") -> Active | L62: =ROUND((IF(F62="",Assumptions!$B$5,F62)-E62)/365.25,1) -> 0.7 | M62: =IF(L62<1,"Under 1 yr",IF(L62<3,"1 to 3 yrs",IF(L62<5,"3 to 5 yrs","5+ yrs"))) -> Under 1 yr | N62: =H62*12 -> 828000 | O62: =IF(AND(E62<Assumptions!$B$6,OR(F62="",F62>=Assumptions!$B$6)),1,0) -> 0 | P62: =IF(F62="",0,IF(AND(F62>=Assumptions!$B$6,F62<=Assumptions!$B$5),1,0)) -> 0 | Q62: =P62*N62*Assumptions!$B$7 -> 0 | R62: =IF(AND(P62=1,J62>=Assumptions!$B$10),1,0) -> 0
A63: EMP2062 | B63: Customer Service | C63: Officer | D63: M | E63: 45248 | H63: 90000 | I63: 4 | J63: 3 | K63: =IF(F63="","Active","Left") -> Active | L63: =ROUND((IF(F63="",Assumptions!$B$5,F63)-E63)/365.25,1) -> 2.9 | M63: =IF(L63<1,"Under 1 yr",IF(L63<3,"1 to 3 yrs",IF(L63<5,"3 to 5 yrs","5+ yrs"))) -> 1 to 3 yrs | N63: =H63*12 -> 1080000 | O63: =IF(AND(E63<Assumptions!$B$6,OR(F63="",F63>=Assumptions!$B$6)),1,0) -> 1 | P63: =IF(F63="",0,IF(AND(F63>=Assumptions!$B$6,F63<=Assumptions!$B$5),1,0)) -> 0 | Q63: =P63*N63*Assumptions!$B$7 -> 0 | R63: =IF(AND(P63=1,J63>=Assumptions!$B$10),1,0) -> 0
A64: EMP2063 | B64: Sales | C64: Officer | D64: M | E64: 44532 | H64: 83000 | I64: 9 | J64: 4 | K64: =IF(F64="","Active","Left") -> Active | L64: =ROUND((IF(F64="",Assumptions!$B$5,F64)-E64)/365.25,1) -> 4.8 | M64: =IF(L64<1,"Under 1 yr",IF(L64<3,"1 to 3 yrs",IF(L64<5,"3 to 5 yrs","5+ yrs"))) -> 3 to 5 yrs | N64: =H64*12 -> 996000 | O64: =IF(AND(E64<Assumptions!$B$6,OR(F64="",F64>=Assumptions!$B$6)),1,0) -> 1 | P64: =IF(F64="",0,IF(AND(F64>=Assumptions!$B$6,F64<=Assumptions!$B$5),1,0)) -> 0 | Q64: =P64*N64*Assumptions!$B$7 -> 0 | R64: =IF(AND(P64=1,J64>=Assumptions!$B$10),1,0) -> 0
A65: EMP2064 | B65: HR | C65: Senior | D65: F | E65: 42298 | H65: 159000 | I65: 3 | J65: 4 | K65: =IF(F65="","Active","Left") -> Active | L65: =ROUND((IF(F65="",Assumptions!$B$5,F65)-E65)/365.25,1) -> 10.9 | M65: =IF(L65<1,"Under 1 yr",IF(L65<3,"1 to 3 yrs",IF(L65<5,"3 to 5 yrs","5+ yrs"))) -> 5+ yrs | N65: =H65*12 -> 1908000 | O65: =IF(AND(E65<Assumptions!$B$6,OR(F65="",F65>=Assumptions!$B$6)),1,0) -> 1 | P65: =IF(F65="",0,IF(AND(F65>=Assumptions!$B$6,F65<=Assumptions!$B$5),1,0)) -> 0 | Q65: =P65*N65*Assumptions!$B$7 -> 0 | R65: =IF(AND(P65=1,J65>=Assumptions!$B$10),1,0) -> 0
A66: EMP2065 | B66: Operations | C66: Officer | D66: F | E66: 42420 | H66: 82000 | I66: 5 | J66: 3 | K66: =IF(F66="","Active","Left") -> Active | L66: =ROUND((IF(F66="",Assumptions!$B$5,F66)-E66)/365.25,1) -> 10.6 | M66: =IF(L66<1,"Under 1 yr",IF(L66<3,"1 to 3 yrs",IF(L66<5,"3 to 5 yrs","5+ yrs"))) -> 5+ yrs | N66: =H66*12 -> 984000 | O66: =IF(AND(E66<Assumptions!$B$6,OR(F66="",F66>=Assumptions!$B$6)),1,0) -> 1 | P66: =IF(F66="",0,IF(AND(F66>=Assumptions!$B$6,F66<=Assumptions!$B$5),1,0)) -> 0 | Q66: =P66*N66*Assumptions!$B$7 -> 0 | R66: =IF(AND(P66=1,J66>=Assumptions!$B$10),1,0) -> 0
A67: EMP2066 | B67: Sales | C67: Senior | D67: F | E67: 45446 | H67: 175000 | I67: 8 | J67: 3 | K67: =IF(F67="","Active","Left") -> Active | L67: =ROUND((IF(F67="",Assumptions!$B$5,F67)-E67)/365.25,1) -> 2.3 | M67: =IF(L67<1,"Under 1 yr",IF(L67<3,"1 to 3 yrs",IF(L67<5,"3 to 5 yrs","5+ yrs"))) -> 1 to 3 yrs | N67: =H67*12 -> 2100000 | O67: =IF(AND(E67<Assumptions!$B$6,OR(F67="",F67>=Assumptions!$B$6)),1,0) -> 1 | P67: =IF(F67="",0,IF(AND(F67>=Assumptions!$B$6,F67<=Assumptions!$B$5),1,0)) -> 0 | Q67: =P67*N67*Assumptions!$B$7 -> 0 | R67: =IF(AND(P67=1,J67>=Assumptions!$B$10),1,0) -> 0
A68: EMP2067 | B68: Customer Service | C68: Officer | D68: F | E68: 46195 | F68: 46289 | G68: Career growth | H68: 85000 | I68: 4 | J68: 4 | K68: =IF(F68="","Active","Left") -> Left | L68: =ROUND((IF(F68="",Assumptions!$B$5,F68)-E68)/365.25,1) -> 0.3 | M68: =IF(L68<1,"Under 1 yr",IF(L68<3,"1 to 3 yrs",IF(L68<5,"3 to 5 yrs","5+ yrs"))) -> Under 1 yr | N68: =H68*12 -> 1020000 | O68: =IF(AND(E68<Assumptions!$B$6,OR(F68="",F68>=Assumptions!$B$6)),1,0) -> 0 | P68: =IF(F68="",0,IF(AND(F68>=Assumptions!$B$6,F68<=Assumptions!$B$5),1,0)) -> 1 | Q68: =P68*N68*Assumptions!$B$7 -> 510000 | R68: =IF(AND(P68=1,J68>=Assumptions!$B$10),1,0) -> 1
A69: EMP2068 | B69: Customer Service | C69: Senior | D69: F | E69: 43612 | H69: 174000 | I69: 14 | J69: 2 | K69: =IF(F69="","Active","Left") -> Active | L69: =ROUND((IF(F69="",Assumptions!$B$5,F69)-E69)/365.25,1) -> 7.3 | M69: =IF(L69<1,"Under 1 yr",IF(L69<3,"1 to 3 yrs",IF(L69<5,"3 to 5 yrs","5+ yrs"))) -> 5+ yrs | N69: =H69*12 -> 2088000 | O69: =IF(AND(E69<Assumptions!$B$6,OR(F69="",F69>=Assumptions!$B$6)),1,0) -> 1 | P69: =IF(F69="",0,IF(AND(F69>=Assumptions!$B$6,F69<=Assumptions!$B$5),1,0)) -> 0 | Q69: =P69*N69*Assumptions!$B$7 -> 0 | R69: =IF(AND(P69=1,J69>=Assumptions!$B$10),1,0) -> 0
A70: EMP2069 | B70: Sales | C70: Junior | D70: M | E70: 44213 | H70: 52000 | I70: 2 | J70: 3 | K70: =IF(F70="","Active","Left") -> Active | L70: =ROUND((IF(F70="",Assumptions!$B$5,F70)-E70)/365.25,1) -> 5.7 | M70: =IF(L70<1,"Under 1 yr",IF(L70<3,"1 to 3 yrs",IF(L70<5,"3 to 5 yrs","5+ yrs"))) -> 5+ yrs | N70: =H70*12 -> 624000 | O70: =IF(AND(E70<Assumptions!$B$6,OR(F70="",F70>=Assumptions!$B$6)),1,0) -> 1 | P70: =IF(F70="",0,IF(AND(F70>=Assumptions!$B$6,F70<=Assumptions!$B$5),1,0)) -> 0 | Q70: =P70*N70*Assumptions!$B$7 -> 0 | R70: =IF(AND(P70=1,J70>=Assumptions!$B$10),1,0) -> 0
A71: EMP2070 | B71: Operations | C71: Junior | D71: F | E71: 44552 | F71: 45241 | G71: Personal / family | H71: 55000 | I71: 6 | J71: 4 | K71: =IF(F71="","Active","Left") -> Left | L71: =ROUND((IF(F71="",Assumptions!$B$5,F71)-E71)/365.25,1) -> 1.9 | M71: =IF(L71<1,"Under 1 yr",IF(L71<3,"1 to 3 yrs",IF(L71<5,"3 to 5 yrs","5+ yrs"))) -> 1 to 3 yrs | N71: =H71*12 -> 660000 | O71: =IF(AND(E71<Assumptions!$B$6,OR(F71="",F71>=Assumptions!$B$6)),1,0) -> 0 | P71: =IF(F71="",0,IF(AND(F71>=Assumptions!$B$6,F71<=Assumptions!$B$5),1,0)) -> 0 | Q71: =P71*N71*Assumptions!$B$7 -> 0 | R71: =IF(AND(P71=1,J71>=Assumptions!$B$10),1,0) -> 0
A72: EMP2071 | B72: Customer Service | C72: Officer | D72: F | E72: 43070 | H72: 100000 | I72: 7 | J72: 3 | K72: =IF(F72="","Active","Left") -> Active | L72: =ROUND((IF(F72="",Assumptions!$B$5,F72)-E72)/365.25,1) -> 8.8 | M72: =IF(L72<1,"Under 1 yr",IF(L72<3,"1 to 3 yrs",IF(L72<5,"3 to 5 yrs","5+ yrs"))) -> 5+ yrs | N72: =H72*12 -> 1200000 | O72: =IF(AND(E72<Assumptions!$B$6,OR(F72="",F72>=Assumptions!$B$6)),1,0) -> 1 | P72: =IF(F72="",0,IF(AND(F72>=Assumptions!$B$6,F72<=Assumptions!$B$5),1,0)) -> 0 | Q72: =P72*N72*Assumptions!$B$7 -> 0 | R72: =IF(AND(P72=1,J72>=Assumptions!$B$10),1,0) -> 0
A73: EMP2072 | B73: Sales | C73: Manager | D73: F | E73: 45658 | H73: 200000 | I73: 1 | J73: 2 | K73: =IF(F73="","Active","Left") -> Active | L73: =ROUND((IF(F73="",Assumptions!$B$5,F73)-E73)/365.25,1) -> 1.7 | M73: =IF(L73<1,"Under 1 yr",IF(L73<3,"1 to 3 yrs",IF(L73<5,"3 to 5 yrs","5+ yrs"))) -> 1 to 3 yrs | N73: =H73*12 -> 2400000 | O73: =IF(AND(E73<Assumptions!$B$6,OR(F73="",F73>=Assumptions!$B$6)),1,0) -> 1 | P73: =IF(F73="",0,IF(AND(F73>=Assumptions!$B$6,F73<=Assumptions!$B$5),1,0)) -> 0 | Q73: =P73*N73*Assumptions!$B$7 -> 0 | R73: =IF(AND(P73=1,J73>=Assumptions!$B$10),1,0) -> 0
A74: EMP2073 | B74: Finance | C74: Officer | D74: M | E74: 43902 | H74: 85000 | I74: 2 | J74: 2 | K74: =IF(F74="","Active","Left") -> Active | L74: =ROUND((IF(F74="",Assumptions!$B$5,F74)-E74)/365.25,1) -> 6.6 | M74: =IF(L74<1,"Under 1 yr",IF(L74<3,"1 to 3 yrs",IF(L74<5,"3 to 5 yrs","5+ yrs"))) -> 5+ yrs | N74: =H74*12 -> 1020000 | O74: =IF(AND(E74<Assumptions!$B$6,OR(F74="",F74>=Assumptions!$B$6)),1,0) -> 1 | P74: =IF(F74="",0,IF(AND(F74>=Assumptions!$B$6,F74<=Assumptions!$B$5),1,0)) -> 0 | Q74: =P74*N74*Assumptions!$B$7 -> 0 | R74: =IF(AND(P74=1,J74>=Assumptions!$B$10),1,0) -> 0
A75: EMP2074 | B75: Sales | C75: Senior | D75: M | E75: 44243 | H75: 118000 | I75: 11 | J75: 4 | K75: =IF(F75="","Active","Left") -> Active | L75: =ROUND((IF(F75="",Assumptions!$B$5,F75)-E75)/365.25,1) -> 5.6 | M75: =IF(L75<1,"Under 1 yr",IF(L75<3,"1 to 3 yrs",IF(L75<5,"3 to 5 yrs","5+ yrs"))) -> 5+ yrs | N75: =H75*12 -> 1416000 | O75: =IF(AND(E75<Assumptions!$B$6,OR(F75="",F75>=Assumptions!$B$6)),1,0) -> 1 | P75: =IF(F75="",0,IF(AND(F75>=Assumptions!$B$6,F75<=Assumptions!$B$5),1,0)) -> 0 | Q75: =P75*N75*Assumptions!$B$7 -> 0 | R75: =IF(AND(P75=1,J75>=Assumptions!$B$10),1,0) -> 0
A76: EMP2075 | B76: Customer Service | C76: Junior | D76: M | E76: 42338 | H76: 38000 | I76: 10 | J76: 4 | K76: =IF(F76="","Active","Left") -> Active | L76: =ROUND((IF(F76="",Assumptions!$B$5,F76)-E76)/365.25,1) -> 10.8 | M76: =IF(L76<1,"Under 1 yr",IF(L76<3,"1 to 3 yrs",IF(L76<5,"3 to 5 yrs","5+ yrs"))) -> 5+ yrs | N76: =H76*12 -> 456000 | O76: =IF(AND(E76<Assumptions!$B$6,OR(F76="",F76>=Assumptions!$B$6)),1,0) -> 1 | P76: =IF(F76="",0,IF(AND(F76>=Assumptions!$B$6,F76<=Assumptions!$B$5),1,0)) -> 0 | Q76: =P76*N76*Assumptions!$B$7 -> 0 | R76: =IF(AND(P76=1,J76>=Assumptions!$B$10),1,0) -> 0
A77: EMP2076 | B77: Sales | C77: Senior | D77: F | E77: 44491 | H77: 127000 | I77: 2 | J77: 4 | K77: =IF(F77="","Active","Left") -> Active | L77: =ROUND((IF(F77="",Assumptions!$B$5,F77)-E77)/365.25,1) -> 4.9 | M77: =IF(L77<1,"Under 1 yr",IF(L77<3,"1 to 3 yrs",IF(L77<5,"3 to 5 yrs","5+ yrs"))) -> 3 to 5 yrs | N77: =H77*12 -> 1524000 | O77: =IF(AND(E77<Assumptions!$B$6,OR(F77="",F77>=Assumptions!$B$6)),1,0) -> 1 | P77: =IF(F77="",0,IF(AND(F77>=Assumptions!$B$6,F77<=Assumptions!$B$5),1,0)) -> 0 | Q77: =P77*N77*Assumptions!$B$7 -> 0 | R77: =IF(AND(P77=1,J77>=Assumptions!$B$10),1,0) -> 0
A78: EMP2077 | B78: HR | C78: Senior | D78: M | E78: 43721 | H78: 172000 | I78: 6 | J78: 4 | K78: =IF(F78="","Active","Left") -> Active | L78: =ROUND((IF(F78="",Assumptions!$B$5,F78)-E78)/365.25,1) -> 7 | M78: =IF(L78<1,"Under 1 yr",IF(L78<3,"1 to 3 yrs",IF(L78<5,"3 to 5 yrs","5+ yrs"))) -> 5+ yrs | N78: =H78*12 -> 2064000 | O78: =IF(AND(E78<Assumptions!$B$6,OR(F78="",F78>=Assumptions!$B$6)),1,0) -> 1 | P78: =IF(F78="",0,IF(AND(F78>=Assumptions!$B$6,F78<=Assumptions!$B$5),1,0)) -> 0 | Q78: =P78*N78*Assumptions!$B$7 -> 0 | R78: =IF(AND(P78=1,J78>=Assumptions!$B$10),1,0) -> 0
A79: EMP2078 | B79: HR | C79: Senior | D79: M | E79: 44625 | H79: 172000 | I79: 4 | J79: 3 | K79: =IF(F79="","Active","Left") -> Active | L79: =ROUND((IF(F79="",Assumptions!$B$5,F79)-E79)/365.25,1) -> 4.6 | M79: =IF(L79<1,"Under 1 yr",IF(L79<3,"1 to 3 yrs",IF(L79<5,"3 to 5 yrs","5+ yrs"))) -> 3 to 5 yrs | N79: =H79*12 -> 2064000 | O79: =IF(AND(E79<Assumptions!$B$6,OR(F79="",F79>=Assumptions!$B$6)),1,0) -> 1 | P79: =IF(F79="",0,IF(AND(F79>=Assumptions!$B$6,F79<=Assumptions!$B$5),1,0)) -> 0 | Q79: =P79*N79*Assumptions!$B$7 -> 0 | R79: =IF(AND(P79=1,J79>=Assumptions!$B$10),1,0) -> 0
A80: EMP2079 | B80: Finance | C80: Officer | D80: M | E80: 43904 | H80: 90000 | I80: 5 | J80: 3 | K80: =IF(F80="","Active","Left") -> Active | L80: =ROUND((IF(F80="",Assumptions!$B$5,F80)-E80)/365.25,1) -> 6.5 | M80: =IF(L80<1,"Under 1 yr",IF(L80<3,"1 to 3 yrs",IF(L80<5,"3 to 5 yrs","5+ yrs"))) -> 5+ yrs | N80: =H80*12 -> 1080000 | O80: =IF(AND(E80<Assumptions!$B$6,OR(F80="",F80>=Assumptions!$B$6)),1,0) -> 1 | P80: =IF(F80="",0,IF(AND(F80>=Assumptions!$B$6,F80<=Assumptions!$B$5),1,0)) -> 0 | Q80: =P80*N80*Assumptions!$B$7 -> 0 | R80: =IF(AND(P80=1,J80>=Assumptions!$B$10),1,0) -> 0
A81: EMP2080 | B81: Customer Service | C81: Officer | D81: F | E81: 42257 | H81: 97000 | I81: 3 | J81: 3 | K81: =IF(F81="","Active","Left") -> Active | L81: =ROUND((IF(F81="",Assumptions!$B$5,F81)-E81)/365.25,1) -> 11.1 | M81: =IF(L81<1,"Under 1 yr",IF(L81<3,"1 to 3 yrs",IF(L81<5,"3 to 5 yrs","5+ yrs"))) -> 5+ yrs | N81: =H81*12 -> 1164000 | O81: =IF(AND(E81<Assumptions!$B$6,OR(F81="",F81>=Assumptions!$B$6)),1,0) -> 1 | P81: =IF(F81="",0,IF(AND(F81>=Assumptions!$B$6,F81<=Assumptions!$B$5),1,0)) -> 0 | Q81: =P81*N81*Assumptions!$B$7 -> 0 | R81: =IF(AND(P81=1,J81>=Assumptions!$B$10),1,0) -> 0
A82: EMP2081 | B82: IT | C82: Junior | D82: F | E82: 45567 | H82: 54000 | I82: 1 | J82: 4 | K82: =IF(F82="","Active","Left") -> Active | L82: =ROUND((IF(F82="",Assumptions!$B$5,F82)-E82)/365.25,1) -> 2 | M82: =IF(L82<1,"Under 1 yr",IF(L82<3,"1 to 3 yrs",IF(L82<5,"3 to 5 yrs","5+ yrs"))) -> 1 to 3 yrs | N82: =H82*12 -> 648000 | O82: =IF(AND(E82<Assumptions!$B$6,OR(F82="",F82>=Assumptions!$B$6)),1,0) -> 1 | P82: =IF(F82="",0,IF(AND(F82>=Assumptions!$B$6,F82<=Assumptions!$B$5),1,0)) -> 0 | Q82: =P82*N82*Assumptions!$B$7 -> 0 | R82: =IF(AND(P82=1,J82>=Assumptions!$B$10),1,0) -> 0
A83: EMP2082 | B83: Finance | C83: Junior | D83: F | E83: 46224 | H83: 50000 | I83: 6 | J83: 5 | K83: =IF(F83="","Active","Left") -> Active | L83: =ROUND((IF(F83="",Assumptions!$B$5,F83)-E83)/365.25,1) -> 0.2 | M83: =IF(L83<1,"Under 1 yr",IF(L83<3,"1 to 3 yrs",IF(L83<5,"3 to 5 yrs","5+ yrs"))) -> Under 1 yr | N83: =H83*12 -> 600000 | O83: =IF(AND(E83<Assumptions!$B$6,OR(F83="",F83>=Assumptions!$B$6)),1,0) -> 0 | P83: =IF(F83="",0,IF(AND(F83>=Assumptions!$B$6,F83<=Assumptions!$B$5),1,0)) -> 0 | Q83: =P83*N83*Assumptions!$B$7 -> 0 | R83: =IF(AND(P83=1,J83>=Assumptions!$B$10),1,0) -> 0
A84: EMP2083 | B84: Customer Service | C84: Junior | D84: F | E84: 43328 | F84: 46123 | G84: Relocation | H84: 52000 | I84: 4 | J84: 3 | K84: =IF(F84="","Active","Left") -> Left | L84: =ROUND((IF(F84="",Assumptions!$B$5,F84)-E84)/365.25,1) -> 7.7 | M84: =IF(L84<1,"Under 1 yr",IF(L84<3,"1 to 3 yrs",IF(L84<5,"3 to 5 yrs","5+ yrs"))) -> 5+ yrs | N84: =H84*12 -> 624000 | O84: =IF(AND(E84<Assumptions!$B$6,OR(F84="",F84>=Assumptions!$B$6)),1,0) -> 1 | P84: =IF(F84="",0,IF(AND(F84>=Assumptions!$B$6,F84<=Assumptions!$B$5),1,0)) -> 1 | Q84: =P84*N84*Assumptions!$B$7 -> 312000 | R84: =IF(AND(P84=1,J84>=Assumptions!$B$10),1,0) -> 0
A85: EMP2084 | B85: Sales | C85: Officer | D85: M | E85: 45929 | H85: 62000 | I85: 4 | J85: 4 | K85: =IF(F85="","Active","Left") -> Active | L85: =ROUND((IF(F85="",Assumptions!$B$5,F85)-E85)/365.25,1) -> 1 | M85: =IF(L85<1,"Under 1 yr",IF(L85<3,"1 to 3 yrs",IF(L85<5,"3 to 5 yrs","5+ yrs"))) -> 1 to 3 yrs | N85: =H85*12 -> 744000 | O85: =IF(AND(E85<Assumptions!$B$6,OR(F85="",F85>=Assumptions!$B$6)),1,0) -> 1 | P85: =IF(F85="",0,IF(AND(F85>=Assumptions!$B$6,F85<=Assumptions!$B$5),1,0)) -> 0 | Q85: =P85*N85*Assumptions!$B$7 -> 0 | R85: =IF(AND(P85=1,J85>=Assumptions!$B$10),1,0) -> 0
A86: EMP2085 | B86: HR | C86: Junior | D86: M | E86: 43454 | H86: 59000 | I86: 7 | J86: 4 | K86: =IF(F86="","Active","Left") -> Active | L86: =ROUND((IF(F86="",Assumptions!$B$5,F86)-E86)/365.25,1) -> 7.8 | M86: =IF(L86<1,"Under 1 yr",IF(L86<3,"1 to 3 yrs",IF(L86<5,"3 to 5 yrs","5+ yrs"))) -> 5+ yrs | N86: =H86*12 -> 708000 | O86: =IF(AND(E86<Assumptions!$B$6,OR(F86="",F86>=Assumptions!$B$6)),1,0) -> 1 | P86: =IF(F86="",0,IF(AND(F86>=Assumptions!$B$6,F86<=Assumptions!$B$5),1,0)) -> 0 | Q86: =P86*N86*Assumptions!$B$7 -> 0 | R86: =IF(AND(P86=1,J86>=Assumptions!$B$10),1,0) -> 0
A87: EMP2086 | B87: IT | C87: Senior | D87: M | E87: 42081 | F87: 46259 | G87: Career growth | H87: 145000 | I87: 2 | J87: 2 | K87: =IF(F87="","Active","Left") -> Left | L87: =ROUND((IF(F87="",Assumptions!$B$5,F87)-E87)/365.25,1) -> 11.4 | M87: =IF(L87<1,"Under 1 yr",IF(L87<3,"1 to 3 yrs",IF(L87<5,"3 to 5 yrs","5+ yrs"))) -> 5+ yrs | N87: =H87*12 -> 1740000 | O87: =IF(AND(E87<Assumptions!$B$6,OR(F87="",F87>=Assumptions!$B$6)),1,0) -> 1 | P87: =IF(F87="",0,IF(AND(F87>=Assumptions!$B$6,F87<=Assumptions!$B$5),1,0)) -> 1 | Q87: =P87*N87*Assumptions!$B$7 -> 870000 | R87: =IF(AND(P87=1,J87>=Assumptions!$B$10),1,0) -> 0
A88: EMP2087 | B88: Customer Service | C88: Senior | D88: F | E88: 46081 | H88: 126000 | I88: 9 | J88: 3 | K88: =IF(F88="","Active","Left") -> Active | L88: =ROUND((IF(F88="",Assumptions!$B$5,F88)-E88)/365.25,1) -> 0.6 | M88: =IF(L88<1,"Under 1 yr",IF(L88<3,"1 to 3 yrs",IF(L88<5,"3 to 5 yrs","5+ yrs"))) -> Under 1 yr | N88: =H88*12 -> 1512000 | O88: =IF(AND(E88<Assumptions!$B$6,OR(F88="",F88>=Assumptions!$B$6)),1,0) -> 0 | P88: =IF(F88="",0,IF(AND(F88>=Assumptions!$B$6,F88<=Assumptions!$B$5),1,0)) -> 0 | Q88: =P88*N88*Assumptions!$B$7 -> 0 | R88: =IF(AND(P88=1,J88>=Assumptions!$B$10),1,0) -> 0
A89: EMP2088 | B89: Operations | C89: Junior | D89: F | E89: 45050 | H89: 36000 | I89: 8 | J89: 4 | K89: =IF(F89="","Active","Left") -> Active | L89: =ROUND((IF(F89="",Assumptions!$B$5,F89)-E89)/365.25,1) -> 3.4 | M89: =IF(L89<1,"Under 1 yr",IF(L89<3,"1 to 3 yrs",IF(L89<5,"3 to 5 yrs","5+ yrs"))) -> 3 to 5 yrs | N89: =H89*12 -> 432000 | O89: =IF(AND(E89<Assumptions!$B$6,OR(F89="",F89>=Assumptions!$B$6)),1,0) -> 1 | P89: =IF(F89="",0,IF(AND(F89>=Assumptions!$B$6,F89<=Assumptions!$B$5),1,0)) -> 0 | Q89: =P89*N89*Assumptions!$B$7 -> 0 | R89: =IF(AND(P89=1,J89>=Assumptions!$B$10),1,0) -> 0
A90: EMP2089 | B90: Customer Service | C90: Junior | D90: F | E90: 45299 | H90: 60000 | I90: 7 | J90: 4 | K90: =IF(F90="","Active","Left") -> Active | L90: =ROUND((IF(F90="",Assumptions!$B$5,F90)-E90)/365.25,1) -> 2.7 | M90: =IF(L90<1,"Under 1 yr",IF(L90<3,"1 to 3 yrs",IF(L90<5,"3 to 5 yrs","5+ yrs"))) -> 1 to 3 yrs | N90: =H90*12 -> 720000 | O90: =IF(AND(E90<Assumptions!$B$6,OR(F90="",F90>=Assumptions!$B$6)),1,0) -> 1 | P90: =IF(F90="",0,IF(AND(F90>=Assumptions!$B$6,F90<=Assumptions!$B$5),1,0)) -> 0 | Q90: =P90*N90*Assumptions!$B$7 -> 0 | R90: =IF(AND(P90=1,J90>=Assumptions!$B$10),1,0) -> 0
A91: EMP2090 | B91: Customer Service | C91: Senior | D91: F | E91: 42556 | F91: 46135 | G91: Relocation | H91: 132000 | I91: 9 | J91: 4 | K91: =IF(F91="","Active","Left") -> Left | L91: =ROUND((IF(F91="",Assumptions!$B$5,F91)-E91)/365.25,1) -> 9.8 | M91: =IF(L91<1,"Under 1 yr",IF(L91<3,"1 to 3 yrs",IF(L91<5,"3 to 5 yrs","5+ yrs"))) -> 5+ yrs | N91: =H91*12 -> 1584000 | O91: =IF(AND(E91<Assumptions!$B$6,OR(F91="",F91>=Assumptions!$B$6)),1,0) -> 1 | P91: =IF(F91="",0,IF(AND(F91>=Assumptions!$B$6,F91<=Assumptions!$B$5),1,0)) -> 1 | Q91: =P91*N91*Assumptions!$B$7 -> 792000 | R91: =IF(AND(P91=1,J91>=Assumptions!$B$10),1,0) -> 1
A92: EMP2091 | B92: Operations | C92: Officer | D92: F | E92: 42836 | H92: 94000 | I92: 4 | J92: 3 | K92: =IF(F92="","Active","Left") -> Active | L92: =ROUND((IF(F92="",Assumptions!$B$5,F92)-E92)/365.25,1) -> 9.5 | M92: =IF(L92<1,"Under 1 yr",IF(L92<3,"1 to 3 yrs",IF(L92<5,"3 to 5 yrs","5+ yrs"))) -> 5+ yrs | N92: =H92*12 -> 1128000 | O92: =IF(AND(E92<Assumptions!$B$6,OR(F92="",F92>=Assumptions!$B$6)),1,0) -> 1 | P92: =IF(F92="",0,IF(AND(F92>=Assumptions!$B$6,F92<=Assumptions!$B$5),1,0)) -> 0 | Q92: =P92*N92*Assumptions!$B$7 -> 0 | R92: =IF(AND(P92=1,J92>=Assumptions!$B$10),1,0) -> 0
A93: EMP2092 | B93: Sales | C93: Junior | D93: M | E93: 42423 | H93: 43000 | I93: 4 | J93: 3 | K93: =IF(F93="","Active","Left") -> Active | L93: =ROUND((IF(F93="",Assumptions!$B$5,F93)-E93)/365.25,1) -> 10.6 | M93: =IF(L93<1,"Under 1 yr",IF(L93<3,"1 to 3 yrs",IF(L93<5,"3 to 5 yrs","5+ yrs"))) -> 5+ yrs | N93: =H93*12 -> 516000 | O93: =IF(AND(E93<Assumptions!$B$6,OR(F93="",F93>=Assumptions!$B$6)),1,0) -> 1 | P93: =IF(F93="",0,IF(AND(F93>=Assumptions!$B$6,F93<=Assumptions!$B$5),1,0)) -> 0 | Q93: =P93*N93*Assumptions!$B$7 -> 0 | R93: =IF(AND(P93=1,J93>=Assumptions!$B$10),1,0) -> 0
A94: EMP2093 | B94: IT | C94: Manager | D94: M | E94: 42387 | F94: 42574 | G94: Career growth | H94: 242000 | I94: 2 | J94: 4 | K94: =IF(F94="","Active","Left") -> Left | L94: =ROUND((IF(F94="",Assumptions!$B$5,F94)-E94)/365.25,1) -> 0.5 | M94: =IF(L94<1,"Under 1 yr",IF(L94<3,"1 to 3 yrs",IF(L94<5,"3 to 5 yrs","5+ yrs"))) -> Under 1 yr | N94: =H94*12 -> 2904000 | O94: =IF(AND(E94<Assumptions!$B$6,OR(F94="",F94>=Assumptions!$B$6)),1,0) -> 0 | P94: =IF(F94="",0,IF(AND(F94>=Assumptions!$B$6,F94<=Assumptions!$B$5),1,0)) -> 0 | Q94: =P94*N94*Assumptions!$B$7 -> 0 | R94: =IF(AND(P94=1,J94>=Assumptions!$B$10),1,0) -> 0
A95: EMP2094 | B95: HR | C95: Senior | D95: M | E95: 44559 | F95: 46108 | G95: Better pay elsewhere | H95: 166000 | I95: 3 | J95: 4 | K95: =IF(F95="","Active","Left") -> Left | L95: =ROUND((IF(F95="",Assumptions!$B$5,F95)-E95)/365.25,1) -> 4.2 | M95: =IF(L95<1,"Under 1 yr",IF(L95<3,"1 to 3 yrs",IF(L95<5,"3 to 5 yrs","5+ yrs"))) -> 3 to 5 yrs | N95: =H95*12 -> 1992000 | O95: =IF(AND(E95<Assumptions!$B$6,OR(F95="",F95>=Assumptions!$B$6)),1,0) -> 1 | P95: =IF(F95="",0,IF(AND(F95>=Assumptions!$B$6,F95<=Assumptions!$B$5),1,0)) -> 1 | Q95: =P95*N95*Assumptions!$B$7 -> 996000 | R95: =IF(AND(P95=1,J95>=Assumptions!$B$10),1,0) -> 1
A96: EMP2095 | B96: Finance | C96: Officer | D96: M | E96: 44771 | H96: 84000 | I96: 5 | J96: 4 | K96: =IF(F96="","Active","Left") -> Active | L96: =ROUND((IF(F96="",Assumptions!$B$5,F96)-E96)/365.25,1) -> 4.2 | M96: =IF(L96<1,"Under 1 yr",IF(L96<3,"1 to 3 yrs",IF(L96<5,"3 to 5 yrs","5+ yrs"))) -> 3 to 5 yrs | N96: =H96*12 -> 1008000 | O96: =IF(AND(E96<Assumptions!$B$6,OR(F96="",F96>=Assumptions!$B$6)),1,0) -> 1 | P96: =IF(F96="",0,IF(AND(F96>=Assumptions!$B$6,F96<=Assumptions!$B$5),1,0)) -> 0 | Q96: =P96*N96*Assumptions!$B$7 -> 0 | R96: =IF(AND(P96=1,J96>=Assumptions!$B$10),1,0) -> 0
A97: EMP2096 | B97: Sales | C97: Junior | D97: M | E97: 45244 | H97: 36000 | I97: 4 | J97: 3 | K97: =IF(F97="","Active","Left") -> Active | L97: =ROUND((IF(F97="",Assumptions!$B$5,F97)-E97)/365.25,1) -> 2.9 | M97: =IF(L97<1,"Under 1 yr",IF(L97<3,"1 to 3 yrs",IF(L97<5,"3 to 5 yrs","5+ yrs"))) -> 1 to 3 yrs | N97: =H97*12 -> 432000 | O97: =IF(AND(E97<Assumptions!$B$6,OR(F97="",F97>=Assumptions!$B$6)),1,0) -> 1 | P97: =IF(F97="",0,IF(AND(F97>=Assumptions!$B$6,F97<=Assumptions!$B$5),1,0)) -> 0 | Q97: =P97*N97*Assumptions!$B$7 -> 0 | R97: =IF(AND(P97=1,J97>=Assumptions!$B$10),1,0) -> 0
A98: EMP2097 | B98: Customer Service | C98: Senior | D98: F | E98: 44117 | F98: 46061 | G98: Career growth | H98: 166000 | I98: 8 | J98: 5 | K98: =IF(F98="","Active","Left") -> Left | L98: =ROUND((IF(F98="",Assumptions!$B$5,F98)-E98)/365.25,1) -> 5.3 | M98: =IF(L98<1,"Under 1 yr",IF(L98<3,"1 to 3 yrs",IF(L98<5,"3 to 5 yrs","5+ yrs"))) -> 5+ yrs | N98: =H98*12 -> 1992000 | O98: =IF(AND(E98<Assumptions!$B$6,OR(F98="",F98>=Assumptions!$B$6)),1,0) -> 1 | P98: =IF(F98="",0,IF(AND(F98>=Assumptions!$B$6,F98<=Assumptions!$B$5),1,0)) -> 1 | Q98: =P98*N98*Assumptions!$B$7 -> 996000 | R98: =IF(AND(P98=1,J98>=Assumptions!$B$10),1,0) -> 1
A99: EMP2098 | B99: Customer Service | C99: Junior | D99: F | E99: 44244 | H99: 58000 | I99: 9 | J99: 4 | K99: =IF(F99="","Active","Left") -> Active | L99: =ROUND((IF(F99="",Assumptions!$B$5,F99)-E99)/365.25,1) -> 5.6 | M99: =IF(L99<1,"Under 1 yr",IF(L99<3,"1 to 3 yrs",IF(L99<5,"3 to 5 yrs","5+ yrs"))) -> 5+ yrs | N99: =H99*12 -> 696000 | O99: =IF(AND(E99<Assumptions!$B$6,OR(F99="",F99>=Assumptions!$B$6)),1,0) -> 1 | P99: =IF(F99="",0,IF(AND(F99>=Assumptions!$B$6,F99<=Assumptions!$B$5),1,0)) -> 0 | Q99: =P99*N99*Assumptions!$B$7 -> 0 | R99: =IF(AND(P99=1,J99>=Assumptions!$B$10),1,0) -> 0
A100: EMP2099 | B100: Sales | C100: Junior | D100: F | E100: 44892 | H100: 54000 | I100: 4 | J100: 1 | K100: =IF(F100="","Active","Left") -> Active | L100: =ROUND((IF(F100="",Assumptions!$B$5,F100)-E100)/365.25,1) -> 3.8 | M100: =IF(L100<1,"Under 1 yr",IF(L100<3,"1 to 3 yrs",IF(L100<5,"3 to 5 yrs","5+ yrs"))) -> 3 to 5 yrs | N100: =H100*12 -> 648000 | O100: =IF(AND(E100<Assumptions!$B$6,OR(F100="",F100>=Assumptions!$B$6)),1,0) -> 1 | P100: =IF(F100="",0,IF(AND(F100>=Assumptions!$B$6,F100<=Assumptions!$B$5),1,0)) -> 0 | Q100: =P100*N100*Assumptions!$B$7 -> 0 | R100: =IF(AND(P100=1,J100>=Assumptions!$B$10),1,0) -> 0
...
