Workbook

Sheet README
A1: Loan Portfolio & Credit Risk (SACCO / Microfinance)
A3: Business scenario | B3: A Kenyan SACCO wants to know how healthy its loan book is: how much is in arrears, which branches and products are driving risk, and whether provisions are adequate. This workbook turns a loan ledger into PAR30/PAR90, ageing buckets and a provisioning estimate.
A5: Sheets | B5: Assumptions: PAR thresholds, target PAR30 and the provision rate per ageing bucket.
B6: Loans: 400 synthetic loans (inputs) plus formula columns for bucket, provision, PAR30 and PAR90 balances.
B7: Dashboard: portfolio KPIs, formula-driven insights, tables by branch, product and ageing bucket, and charts.
A9: Colour legend | B9: Blue text on yellow = editable input (Assumptions sheet).
B10: Blue header on Data sheet = raw input columns; green header = formula columns (do not overwrite).
B11: Black text = formula. Everything on the Dashboard recalculates when Assumptions or Data change.
A13: Data note | B13: All data is SYNTHETIC, generated for portfolio demonstration. Targets and thresholds are illustrative. Not client data.
A15: Skills demonstrated | B15: Portfolio at Risk (PAR) analysis
B16: Ageing buckets and provisioning
B17: SUMIFS / COUNTIFS / INDEX-MATCH
B18: Assumption-driven modelling
B19: Dashboard design

Sheet Dashboard
A1: Loan Portfolio & Credit Risk Dashboard
A2: Synthetic data | KES | All figures formula-driven
A4: Key metrics
A5: Active loans | B5: =COUNTA(Loans!$A$2:$A$401) -> 400
A6: Gross loan book (KES) | B6: =SUM(Loans!$H$2:$H$401) -> 79399400
A7: PAR30 | B7: =SUM(Loans!$M$2:$M$401)/SUM(Loans!$H$2:$H$401) -> 0.13271385
A8: PAR90 (non-performing) | B8: =SUM(Loans!$N$2:$N$401)/SUM(Loans!$H$2:$H$401) -> 0.046369368
A9: Total provision (KES) | B9: =SUM(Loans!$L$2:$L$401) -> 5363877
A10: Provision / gross book | B10: =SUM(Loans!$L$2:$L$401)/SUM(Loans!$H$2:$H$401) -> 0.067555636
A11: Provision / PAR90 balance | B11: =IF(SUM(Loans!$N$2:$N$401)=0,0,SUM(Loans!$L$2:$L$401)/SUM(Loans!$N$2:$N$401)) -> 1.4569022
A12: PAR30 vs target | B12: =IF(B7<=Assumptions!$B$7,"Within target","Above target") -> Above target
A14: Insights (auto-updating)
A15: Highest-risk branch (PAR30) | B15: =INDEX(A21:A26,MATCH(MAX(E21:E26),E21:E26,0)) -> Sotik
A16: Highest-risk product (PAR30) | B16: =INDEX(A31:A35,MATCH(MAX(E31:E35),E31:E35,0)) -> Agribusiness Loan
A17: Book more than 30 days late | B17: =SUMIFS(C40:C44,A40:A44,"31-90 days")/SUM(C40:C44)+SUMIFS(C40:C44,A40:A44,"91-180 days")/SUM(C40:C44)+SUMIFS(C40:C44,A40:A44,"180+ days")/SUM(C40:C44) -> 0.13271385
A19: Risk by branch
A20: Branch | B20: Loans | C20: Balance (KES) | D20: PAR30 balance (KES) | E20: PAR30 % | F20: PAR90 % | G20: Provision (KES) | H20: Share of book | I20: vs target
A21: Bomet | B21: =COUNTIFS(Loans!$B$2:$B$401,$A21) -> 102 | C21: =SUMIFS(Loans!$H$2:$H$401,Loans!$B$2:$B$401,$A21) -> 19142400 | D21: =SUMIFS(Loans!$M$2:$M$401,Loans!$B$2:$B$401,$A21) -> 3244900 | E21: =IF(C21=0,0,D21/C21) -> 0.16951375 | F21: =IF(C21=0,0,SUMIFS(Loans!$N$2:$N$401,Loans!$B$2:$B$401,$A21)/C21) -> 0.054585632 | G21: =SUMIFS(Loans!$L$2:$L$401,Loans!$B$2:$B$401,$A21) -> 1281145 | H21: =C21/SUM(C$21:C$26) -> 0.24108998 | I21: =IF(E21<=Assumptions!$B$7,"OK","Above target") -> Above target
A22: Kericho | B22: =COUNTIFS(Loans!$B$2:$B$401,$A22) -> 56 | C22: =SUMIFS(Loans!$H$2:$H$401,Loans!$B$2:$B$401,$A22) -> 11467300 | D22: =SUMIFS(Loans!$M$2:$M$401,Loans!$B$2:$B$401,$A22) -> 1119200 | E22: =IF(C22=0,0,D22/C22) -> 0.097599261 | F22: =IF(C22=0,0,SUMIFS(Loans!$N$2:$N$401,Loans!$B$2:$B$401,$A22)/C22) -> 0.038457178 | G22: =SUMIFS(Loans!$L$2:$L$401,Loans!$B$2:$B$401,$A22) -> 618655 | H22: =C22/SUM(C$21:C$26) -> 0.14442552 | I22: =IF(E22<=Assumptions!$B$7,"OK","Above target") -> Above target
A23: Sotik | B23: =COUNTIFS(Loans!$B$2:$B$401,$A23) -> 58 | C23: =SUMIFS(Loans!$H$2:$H$401,Loans!$B$2:$B$401,$A23) -> 11743200 | D23: =SUMIFS(Loans!$M$2:$M$401,Loans!$B$2:$B$401,$A23) -> 2800100 | E23: =IF(C23=0,0,D23/C23) -> 0.23844438 | F23: =IF(C23=0,0,SUMIFS(Loans!$N$2:$N$401,Loans!$B$2:$B$401,$A23)/C23) -> 0.092879283 | G23: =SUMIFS(Loans!$L$2:$L$401,Loans!$B$2:$B$401,$A23) -> 1404137 | H23: =C23/SUM(C$21:C$26) -> 0.14790036 | I23: =IF(E23<=Assumptions!$B$7,"OK","Above target") -> Above target
A24: Litein | B24: =COUNTIFS(Loans!$B$2:$B$401,$A24) -> 63 | C24: =SUMIFS(Loans!$H$2:$H$401,Loans!$B$2:$B$401,$A24) -> 11679500 | D24: =SUMIFS(Loans!$M$2:$M$401,Loans!$B$2:$B$401,$A24) -> 1407700 | E24: =IF(C24=0,0,D24/C24) -> 0.12052742 | F24: =IF(C24=0,0,SUMIFS(Loans!$N$2:$N$401,Loans!$B$2:$B$401,$A24)/C24) -> 0.058504217 | G24: =SUMIFS(Loans!$L$2:$L$401,Loans!$B$2:$B$401,$A24) -> 997220 | H24: =C24/SUM(C$21:C$26) -> 0.14709809 | I24: =IF(E24<=Assumptions!$B$7,"OK","Above target") -> Above target
A25: Nakuru | B25: =COUNTIFS(Loans!$B$2:$B$401,$A25) -> 66 | C25: =SUMIFS(Loans!$H$2:$H$401,Loans!$B$2:$B$401,$A25) -> 12745500 | D25: =SUMIFS(Loans!$M$2:$M$401,Loans!$B$2:$B$401,$A25) -> 172100 | E25: =IF(C25=0,0,D25/C25) -> 0.013502805 | F25: =IF(C25=0,0,SUMIFS(Loans!$N$2:$N$401,Loans!$B$2:$B$401,$A25)/C25) -> 0.0088501824 | G25: =SUMIFS(Loans!$L$2:$L$401,Loans!$B$2:$B$401,$A25) -> 242371 | H25: =C25/SUM(C$21:C$26) -> 0.16052388 | I25: =IF(E25<=Assumptions!$B$7,"OK","Above target") -> OK
A26: Kisii | B26: =COUNTIFS(Loans!$B$2:$B$401,$A26) -> 55 | C26: =SUMIFS(Loans!$H$2:$H$401,Loans!$B$2:$B$401,$A26) -> 12621500 | D26: =SUMIFS(Loans!$M$2:$M$401,Loans!$B$2:$B$401,$A26) -> 1793400 | E26: =IF(C26=0,0,D26/C26) -> 0.14209088 | F26: =IF(C26=0,0,SUMIFS(Loans!$N$2:$N$401,Loans!$B$2:$B$401,$A26)/C26) -> 0.024482035 | G26: =SUMIFS(Loans!$L$2:$L$401,Loans!$B$2:$B$401,$A26) -> 820349 | H26: =C26/SUM(C$21:C$26) -> 0.15896216 | I26: =IF(E26<=Assumptions!$B$7,"OK","Above target") -> Above target
A29: Risk by product
A30: Product | B30: Loans | C30: Balance (KES) | D30: PAR30 balance (KES) | E30: PAR30 % | F30: PAR90 % | G30: Provision (KES) | H30: Share of book | I30: vs target
A31: Development Loan | B31: =COUNTIFS(Loans!$C$2:$C$401,$A31) -> 65 | C31: =SUMIFS(Loans!$H$2:$H$401,Loans!$C$2:$C$401,$A31) -> 16262600 | D31: =SUMIFS(Loans!$M$2:$M$401,Loans!$C$2:$C$401,$A31) -> 2678400 | E31: =IF(C31=0,0,D31/C31) -> 0.16469691 | F31: =IF(C31=0,0,SUMIFS(Loans!$N$2:$N$401,Loans!$C$2:$C$401,$A31)/C31) -> 0.045687651 | G31: =SUMIFS(Loans!$L$2:$L$401,Loans!$C$2:$C$401,$A31) -> 1027084 | H31: =C31/SUM(C$31:C$35) -> 0.20482019 | I31: =IF(E31<=Assumptions!$B$7,"OK","Above target") -> Above target
A32: Emergency Loan | B32: =COUNTIFS(Loans!$C$2:$C$401,$A32) -> 82 | C32: =SUMIFS(Loans!$H$2:$H$401,Loans!$C$2:$C$401,$A32) -> 3581800 | D32: =SUMIFS(Loans!$M$2:$M$401,Loans!$C$2:$C$401,$A32) -> 679300 | E32: =IF(C32=0,0,D32/C32) -> 0.18965325 | F32: =IF(C32=0,0,SUMIFS(Loans!$N$2:$N$401,Loans!$C$2:$C$401,$A32)/C32) -> 0.067703389 | G32: =SUMIFS(Loans!$L$2:$L$401,Loans!$C$2:$C$401,$A32) -> 314441 | H32: =C32/SUM(C$31:C$35) -> 0.045111172 | I32: =IF(E32<=Assumptions!$B$7,"OK","Above target") -> Above target
A33: Agribusiness Loan | B33: =COUNTIFS(Loans!$C$2:$C$401,$A33) -> 88 | C33: =SUMIFS(Loans!$H$2:$H$401,Loans!$C$2:$C$401,$A33) -> 14641200 | D33: =SUMIFS(Loans!$M$2:$M$401,Loans!$C$2:$C$401,$A33) -> 2873000 | E33: =IF(C33=0,0,D33/C33) -> 0.19622709 | F33: =IF(C33=0,0,SUMIFS(Loans!$N$2:$N$401,Loans!$C$2:$C$401,$A33)/C33) -> 0.082199546 | G33: =SUMIFS(Loans!$L$2:$L$401,Loans!$C$2:$C$401,$A33) -> 1629181 | H33: =C33/SUM(C$31:C$35) -> 0.18439938 | I33: =IF(E33<=Assumptions!$B$7,"OK","Above target") -> Above target
A34: School Fees Loan | B34: =COUNTIFS(Loans!$C$2:$C$401,$A34) -> 80 | C34: =SUMIFS(Loans!$H$2:$H$401,Loans!$C$2:$C$401,$A34) -> 6205500 | D34: =SUMIFS(Loans!$M$2:$M$401,Loans!$C$2:$C$401,$A34) -> 390200 | E34: =IF(C34=0,0,D34/C34) -> 0.062879703 | F34: =IF(C34=0,0,SUMIFS(Loans!$N$2:$N$401,Loans!$C$2:$C$401,$A34)/C34) -> 0.015518492 | G34: =SUMIFS(Loans!$L$2:$L$401,Loans!$C$2:$C$401,$A34) -> 267556 | H34: =C34/SUM(C$31:C$35) -> 0.078155502 | I34: =IF(E34<=Assumptions!$B$7,"OK","Above target") -> Above target
A35: Asset Finance | B35: =COUNTIFS(Loans!$C$2:$C$401,$A35) -> 85 | C35: =SUMIFS(Loans!$H$2:$H$401,Loans!$C$2:$C$401,$A35) -> 38708300 | D35: =SUMIFS(Loans!$M$2:$M$401,Loans!$C$2:$C$401,$A35) -> 3916500 | E35: =IF(C35=0,0,D35/C35) -> 0.10117985 | F35: =IF(C35=0,0,SUMIFS(Loans!$N$2:$N$401,Loans!$C$2:$C$401,$A35)/C35) -> 0.03607495 | G35: =SUMIFS(Loans!$L$2:$L$401,Loans!$C$2:$C$401,$A35) -> 2125615 | H35: =C35/SUM(C$31:C$35) -> 0.48751376 | I35: =IF(E35<=Assumptions!$B$7,"OK","Above target") -> Above target
A38: Ageing buckets
A39: Bucket | B39: Loans | C39: Balance (KES) | D39: Share of book | E39: Provision rate | F39: Provision (KES)
A40: Current | B40: =COUNTIFS(Loans!$J$2:$J$401,$A40) -> 309 | C40: =SUMIFS(Loans!$H$2:$H$401,Loans!$J$2:$J$401,$A40) -> 62398700 | D40: =C40/SUM(C$40:C$44) -> 0.78588377 | E40: =INDEX(Assumptions!$B$11:$B$15,MATCH($A40,Assumptions!$A$11:$A$15,0)) -> 0.01 | F40: =SUMIFS(Loans!$L$2:$L$401,Loans!$J$2:$J$401,$A40) -> 623987
A41: 01-30 days | B41: =COUNTIFS(Loans!$J$2:$J$401,$A41) -> 38 | C41: =SUMIFS(Loans!$H$2:$H$401,Loans!$J$2:$J$401,$A41) -> 6463300 | D41: =C41/SUM(C$40:C$44) -> 0.081402378 | E41: =INDEX(Assumptions!$B$11:$B$15,MATCH($A41,Assumptions!$A$11:$A$15,0)) -> 0.05 | F41: =SUMIFS(Loans!$L$2:$L$401,Loans!$J$2:$J$401,$A41) -> 323165
A42: 31-90 days | B42: =COUNTIFS(Loans!$J$2:$J$401,$A42) -> 30 | C42: =SUMIFS(Loans!$H$2:$H$401,Loans!$J$2:$J$401,$A42) -> 6855700 | D42: =C42/SUM(C$40:C$44) -> 0.086344481 | E42: =INDEX(Assumptions!$B$11:$B$15,MATCH($A42,Assumptions!$A$11:$A$15,0)) -> 0.25 | F42: =SUMIFS(Loans!$L$2:$L$401,Loans!$J$2:$J$401,$A42) -> 1713925
A43: 91-180 days | B43: =COUNTIFS(Loans!$J$2:$J$401,$A43) -> 12 | C43: =SUMIFS(Loans!$H$2:$H$401,Loans!$J$2:$J$401,$A43) -> 1957800 | D43: =C43/SUM(C$40:C$44) -> 0.024657617 | E43: =INDEX(Assumptions!$B$11:$B$15,MATCH($A43,Assumptions!$A$11:$A$15,0)) -> 0.5 | F43: =SUMIFS(Loans!$L$2:$L$401,Loans!$J$2:$J$401,$A43) -> 978900
A44: 180+ days | B44: =COUNTIFS(Loans!$J$2:$J$401,$A44) -> 11 | C44: =SUMIFS(Loans!$H$2:$H$401,Loans!$J$2:$J$401,$A44) -> 1723900 | D44: =C44/SUM(C$40:C$44) -> 0.021711751 | E44: =INDEX(Assumptions!$B$11:$B$15,MATCH($A44,Assumptions!$A$11:$A$15,0)) -> 1 | F44: =SUMIFS(Loans!$L$2:$L$401,Loans!$J$2:$J$401,$A44) -> 1723900

Sheet Assumptions
A1: Assumptions (edit the yellow cells)
A4: Parameter | B4: Value | C4: Note
A5: PAR threshold 1 (days past due >) | B5: 30 | C5: Balances of loans more than this many days late count toward PAR30.
A6: PAR threshold 2 (days past due >) | B6: 90 | C6: Used for PAR90 / non-performing loans.
A7: Target PAR30 | B7: 0.05 | C7: Illustrative internal target.
A9: Provision rate by ageing bucket
A10: Bucket | B10: Provision rate | C10: Note
A11: Current | B11: 0.01 | C11: Illustrative rates; replace with the SACCO/IFRS 9 policy.
A12: 01-30 days | B12: 0.05 | C12: Illustrative rates; replace with the SACCO/IFRS 9 policy.
A13: 31-90 days | B13: 0.25 | C13: Illustrative rates; replace with the SACCO/IFRS 9 policy.
A14: 91-180 days | B14: 0.5 | C14: Illustrative rates; replace with the SACCO/IFRS 9 policy.
A15: 180+ days | B15: 1 | C15: Illustrative rates; replace with the SACCO/IFRS 9 policy.

Sheet Loans
A1: Loan ID | B1: Branch | C1: Product | D1: Disbursed | E1: Amount (KES) | F1: Interest rate (p.a.) | G1: Term (months) | H1: Outstanding balance (KES) | I1: Days past due | J1: Ageing bucket | K1: Provision rate | L1: Provision (KES) | M1: PAR30 balance (KES) | N1: PAR90 balance (KES)
A2: LN1001 | B2: Sotik | C2: Asset Finance | D2: 45486 | E2: 1153000 | F2: 0.16 | G2: 48 | H2: 621300 | I2: 0 | J2: =IF(I2<=0,"Current",IF(I2<=30,"01-30 days",IF(I2<=90,"31-90 days",IF(I2<=180,"91-180 days","180+ days")))) -> Current | K2: =INDEX(Assumptions!$B$11:$B$15,MATCH(J2,Assumptions!$A$11:$A$15,0)) -> 0.01 | L2: =H2*K2 -> 6213 | M2: =IF(I2>Assumptions!$B$5,H2,0) -> 0 | N2: =IF(I2>Assumptions!$B$6,H2,0) -> 0
A3: LN1002 | B3: Bomet | C3: Asset Finance | D3: 45388 | E3: 1174000 | F3: 0.16 | G3: 48 | H3: 789400 | I3: 0 | J3: =IF(I3<=0,"Current",IF(I3<=30,"01-30 days",IF(I3<=90,"31-90 days",IF(I3<=180,"91-180 days","180+ days")))) -> Current | K3: =INDEX(Assumptions!$B$11:$B$15,MATCH(J3,Assumptions!$A$11:$A$15,0)) -> 0.01 | L3: =H3*K3 -> 7894 | M3: =IF(I3>Assumptions!$B$5,H3,0) -> 0 | N3: =IF(I3>Assumptions!$B$6,H3,0) -> 0
A4: LN1003 | B4: Sotik | C4: Emergency Loan | D4: 45941 | E4: 43000 | F4: 0.18 | G4: 6 | H4: 26000 | I4: 0 | J4: =IF(I4<=0,"Current",IF(I4<=30,"01-30 days",IF(I4<=90,"31-90 days",IF(I4<=180,"91-180 days","180+ days")))) -> Current | K4: =INDEX(Assumptions!$B$11:$B$15,MATCH(J4,Assumptions!$A$11:$A$15,0)) -> 0.01 | L4: =H4*K4 -> 260 | M4: =IF(I4>Assumptions!$B$5,H4,0) -> 0 | N4: =IF(I4>Assumptions!$B$6,H4,0) -> 0
A5: LN1004 | B5: Bomet | C5: School Fees Loan | D5: 45453 | E5: 145000 | F5: 0.12 | G5: 12 | H5: 100100 | I5: 0 | J5: =IF(I5<=0,"Current",IF(I5<=30,"01-30 days",IF(I5<=90,"31-90 days",IF(I5<=180,"91-180 days","180+ days")))) -> Current | K5: =INDEX(Assumptions!$B$11:$B$15,MATCH(J5,Assumptions!$A$11:$A$15,0)) -> 0.01 | L5: =H5*K5 -> 1001 | M5: =IF(I5>Assumptions!$B$5,H5,0) -> 0 | N5: =IF(I5>Assumptions!$B$6,H5,0) -> 0
A6: LN1005 | B6: Litein | C6: Asset Finance | D6: 45539 | E6: 329000 | F6: 0.16 | G6: 48 | H6: 80500 | I6: 0 | J6: =IF(I6<=0,"Current",IF(I6<=30,"01-30 days",IF(I6<=90,"31-90 days",IF(I6<=180,"91-180 days","180+ days")))) -> Current | K6: =INDEX(Assumptions!$B$11:$B$15,MATCH(J6,Assumptions!$A$11:$A$15,0)) -> 0.01 | L6: =H6*K6 -> 805 | M6: =IF(I6>Assumptions!$B$5,H6,0) -> 0 | N6: =IF(I6>Assumptions!$B$6,H6,0) -> 0
A7: LN1006 | B7: Litein | C7: School Fees Loan | D7: 45823 | E7: 113000 | F7: 0.12 | G7: 12 | H7: 59900 | I7: 0 | J7: =IF(I7<=0,"Current",IF(I7<=30,"01-30 days",IF(I7<=90,"31-90 days",IF(I7<=180,"91-180 days","180+ days")))) -> Current | K7: =INDEX(Assumptions!$B$11:$B$15,MATCH(J7,Assumptions!$A$11:$A$15,0)) -> 0.01 | L7: =H7*K7 -> 599 | M7: =IF(I7>Assumptions!$B$5,H7,0) -> 0 | N7: =IF(I7>Assumptions!$B$6,H7,0) -> 0
A8: LN1007 | B8: Kericho | C8: Agribusiness Loan | D8: 46152 | E8: 305000 | F8: 0.15 | G8: 24 | H8: 62100 | I8: 322 | J8: =IF(I8<=0,"Current",IF(I8<=30,"01-30 days",IF(I8<=90,"31-90 days",IF(I8<=180,"91-180 days","180+ days")))) -> 180+ days | K8: =INDEX(Assumptions!$B$11:$B$15,MATCH(J8,Assumptions!$A$11:$A$15,0)) -> 1 | L8: =H8*K8 -> 62100 | M8: =IF(I8>Assumptions!$B$5,H8,0) -> 62100 | N8: =IF(I8>Assumptions!$B$6,H8,0) -> 62100
A9: LN1008 | B9: Bomet | C9: Agribusiness Loan | D9: 45322 | E9: 211000 | F9: 0.15 | G9: 24 | H9: 162200 | I9: 0 | J9: =IF(I9<=0,"Current",IF(I9<=30,"01-30 days",IF(I9<=90,"31-90 days",IF(I9<=180,"91-180 days","180+ days")))) -> Current | K9: =INDEX(Assumptions!$B$11:$B$15,MATCH(J9,Assumptions!$A$11:$A$15,0)) -> 0.01 | L9: =H9*K9 -> 1622 | M9: =IF(I9>Assumptions!$B$5,H9,0) -> 0 | N9: =IF(I9>Assumptions!$B$6,H9,0) -> 0
A10: LN1009 | B10: Bomet | C10: Development Loan | D10: 45360 | E10: 510000 | F10: 0.14 | G10: 36 | H10: 143200 | I10: 0 | J10: =IF(I10<=0,"Current",IF(I10<=30,"01-30 days",IF(I10<=90,"31-90 days",IF(I10<=180,"91-180 days","180+ days")))) -> Current | K10: =INDEX(Assumptions!$B$11:$B$15,MATCH(J10,Assumptions!$A$11:$A$15,0)) -> 0.01 | L10: =H10*K10 -> 1432 | M10: =IF(I10>Assumptions!$B$5,H10,0) -> 0 | N10: =IF(I10>Assumptions!$B$6,H10,0) -> 0
A11: LN1010 | B11: Kisii | C11: Development Loan | D11: 45773 | E11: 318000 | F11: 0.14 | G11: 36 | H11: 113600 | I11: 0 | J11: =IF(I11<=0,"Current",IF(I11<=30,"01-30 days",IF(I11<=90,"31-90 days",IF(I11<=180,"91-180 days","180+ days")))) -> Current | K11: =INDEX(Assumptions!$B$11:$B$15,MATCH(J11,Assumptions!$A$11:$A$15,0)) -> 0.01 | L11: =H11*K11 -> 1136 | M11: =IF(I11>Assumptions!$B$5,H11,0) -> 0 | N11: =IF(I11>Assumptions!$B$6,H11,0) -> 0
A12: LN1011 | B12: Kericho | C12: School Fees Loan | D12: 46089 | E12: 137000 | F12: 0.12 | G12: 12 | H12: 34900 | I12: 0 | J12: =IF(I12<=0,"Current",IF(I12<=30,"01-30 days",IF(I12<=90,"31-90 days",IF(I12<=180,"91-180 days","180+ days")))) -> Current | K12: =INDEX(Assumptions!$B$11:$B$15,MATCH(J12,Assumptions!$A$11:$A$15,0)) -> 0.01 | L12: =H12*K12 -> 349 | M12: =IF(I12>Assumptions!$B$5,H12,0) -> 0 | N12: =IF(I12>Assumptions!$B$6,H12,0) -> 0
A13: LN1012 | B13: Litein | C13: Agribusiness Loan | D13: 45395 | E13: 94000 | F13: 0.15 | G13: 24 | H13: 40700 | I13: 14 | J13: =IF(I13<=0,"Current",IF(I13<=30,"01-30 days",IF(I13<=90,"31-90 days",IF(I13<=180,"91-180 days","180+ days")))) -> 01-30 days | K13: =INDEX(Assumptions!$B$11:$B$15,MATCH(J13,Assumptions!$A$11:$A$15,0)) -> 0.05 | L13: =H13*K13 -> 2035 | M13: =IF(I13>Assumptions!$B$5,H13,0) -> 0 | N13: =IF(I13>Assumptions!$B$6,H13,0) -> 0
... A401: LN1400 | B401: Sotik | C401: School Fees Loan | D401: 45530 | E401: 95000 | F401: 0.12 | G401: 12 | H401: 42700 | I401: 0 | J401: =IF(I401<=0,"Current",IF(I401<=30,"01-30 days",IF(I401<=90,"31-90 days",IF(I401<=180,"91-180 days","180+ days")))) -> Current | K401: =INDEX(Assumptions!$B$11:$B$15,MATCH(J401,Assumptions!$A$11:$A$15,0)) -> 0.01 | L401: =H401*K401 -> 427 | M401: =IF(I401>Assumptions!$B$5,H401,0) -> 0 | N401: =IF(I401>Assumptions!$B$6,H401,0) -> 0
